Hardware_architecture/LDPC_codes/cnu_iams.v
// =============================================================================
// cnu_iams.v  —  IAMS Check Node Unit (CNU)
// =============================================================================
// Implements the IAMS CN update from Cui et al., IEEE TCAS-I 2020, Section V.
//
// Equation (10) — four-case IAMS magnitude formula:
//   Let min1, min2 = two smallest incoming magnitudes
//       idx1, idx2 = their positions
//       Δ = min2 − min1  (unsigned)
//
//   For output edge n:
//     n == idx1            : α = τ * min2
//     n == idx2            : α = τ * min1
//     n ∈ Ī(m), Δ == 0    : α = τ * max(min1 − 1, 0)
//     n ∈ Ī(m), Δ != 0    : α = τ * min1
//
//   Sign:  ⊕ of all input signs, then toggle for outgoing edge n.
//
// Fixed-point params (paper Table I):
//   Input message width  : Q_IN  = 7 bits (signed, range −31..+31 with q=4,q̃=6)
//   Scaling factor τ     : implemented as right-shift (τ = 1 gives MS baseline)
//
// Parameterisation:
//   DC   — check-node degree (number of connected variable nodes)
//   QW   — total message bit-width (includes sign bit)
//   IDW  — index bit-width = ceil(log2(DC))
//
// Ports:
//   msg_in[DC-1:0][QW-1:0]  — incoming VN→CN messages (signed 2's complement)
//   msg_out[DC-1:0][QW-1:0] — outgoing CN→VN messages (signed 2's complement)
// =============================================================================

`timescale 1ns / 1ps

module cnu_iams #(
    parameter DC   = 10,          // Check-node degree (max in BG2 = 10)
    parameter QW   = 7,           // Message bit-width (paper: Q̃=31, 6 bits + sign)
    parameter IDW  = 4            // Index width: ceil(log2(DC))
) (
    input  wire                  clk,
    input  wire                  rst_n,
    input  wire                  valid_in,   // Input messages valid this cycle
    // Flattened 2-D input: DC messages each QW bits (signed)
    input  wire [DC*QW-1 : 0]   msg_flat_in,
    output reg  [DC*QW-1 : 0]   msg_flat_out,
    output reg                   valid_out
);

    // -------------------------------------------------------------------------
    // Unpack flat input into array
    // -------------------------------------------------------------------------
    wire signed [QW-1:0] msg_in [0:DC-1];
    genvar gi;
    generate
        for (gi = 0; gi < DC; gi = gi + 1) begin : unpack
            assign msg_in[gi] = msg_flat_in[gi*QW +: QW];
        end
    endgenerate

    // -------------------------------------------------------------------------
    // Internal signals
    // -------------------------------------------------------------------------
    // Magnitudes (unsigned, QW-1 bits)
    wire [QW-2:0] mag [0:DC-1];
    // Signs (1 = negative)
    wire          sgn [0:DC-1];

    generate
        for (gi = 0; gi < DC; gi = gi + 1) begin : mag_sign
            assign sgn[gi] = msg_in[gi][QW-1];
            // magnitude = absolute value
            assign mag[gi] = sgn[gi] ? (~msg_in[gi][QW-2:0] + 1'b1)
                                      : msg_in[gi][QW-2:0];
        end
    endgenerate

    // -------------------------------------------------------------------------
    // Cumulative XOR sign (parity of all signs)
    // -------------------------------------------------------------------------
    reg sign_total;
    integer k;
    always @(*) begin
        sign_total = 1'b0;
        for (k = 0; k < DC; k = k + 1)
            sign_total = sign_total ^ sgn[k];
    end

    // -------------------------------------------------------------------------
    // Find min1, min2, idx1, idx2
    // min1 = smallest magnitude, min2 = second smallest
    // -------------------------------------------------------------------------
    reg [QW-2:0] min1, min2;
    reg [IDW-1:0] idx1, idx2;

    integer i;
    always @(*) begin
        min1 = {(QW-1){1'b1}};   // initialise to max
        min2 = {(QW-1){1'b1}};
        idx1 = {IDW{1'b0}};
        idx2 = {IDW{1'b0}};

        for (i = 0; i < DC; i = i + 1) begin
            if (mag[i] <= min1) begin
                // New minimum: push old min1 to min2
                min2 = min1;
                idx2 = idx1;
                min1 = mag[i];
                idx1 = i[IDW-1:0];
            end else if (mag[i] < min2) begin
                min2 = mag[i];
                idx2 = i[IDW-1:0];
            end
        end
    end

    // -------------------------------------------------------------------------
    // Compute Δ = min2 − min1  (unsigned difference, saturated to 0)
    // -------------------------------------------------------------------------
    wire [QW-2:0] delta;
    assign delta = (min2 >= min1) ? (min2 - min1) : {(QW-1){1'b0}};

    // -------------------------------------------------------------------------
    // IAMS CN update — combinational
    // -------------------------------------------------------------------------
    // Output messages registered on clock edge
    reg signed [QW-1:0] msg_out_comb [0:DC-1];

    integer n;
    reg [QW-2:0] alpha_mag;   // unsigned magnitude of output
    reg          out_sign;

    always @(*) begin
        for (n = 0; n < DC; n = n + 1) begin
            // Sign = total parity XOR own sign (= parity of all OTHER signs)
            out_sign = sign_total ^ sgn[n];

            // ---- IAMS magnitude selection (eq. 10) --------------------------
            if (n[IDW-1:0] == idx1) begin
                // This edge is the minimum index → use min2
                alpha_mag = min2;
            end else if (n[IDW-1:0] == idx2) begin
                // This edge is the second-minimum index → use min1
                alpha_mag = min1;
            end else begin
                // All other edges (Ī(m) set)
                if (delta == {(QW-1){1'b0}}) begin
                    // Δ = 0 → use max(min1 − 1, 0)
                    alpha_mag = (min1 > ({{(QW-2){1'b0}}, 1'b1})) ? (min1 - 1'b1) : ({(QW-1){1'b0}});
                end else begin
                    // Δ ≠ 0 → use min1
                    alpha_mag = min1;
                end
            end

            // ---- Saturate magnitude to max representable ----
            // (mag is QW-1 bits, message is QW bits signed → max mag = 2^(QW-1)-1)
            // Already fits since alpha_mag is QW-1 bits.

            // ---- Reconstruct signed output ----
            if (alpha_mag == {(QW-1){1'b0}}) begin
                msg_out_comb[n] = {QW{1'b0}};         // zero
            end else if (out_sign) begin
                // negative: 2's complement
                msg_out_comb[n] = {1'b1, (~alpha_mag + 1'b1)};
            end else begin
                msg_out_comb[n] = {1'b0, alpha_mag};  // positive
            end
        end
    end

    // -------------------------------------------------------------------------
    // Pipeline register (1 cycle latency for timing closure)
    // -------------------------------------------------------------------------
    integer p;
    always @(posedge clk or negedge rst_n) begin
        if (!rst_n) begin
            msg_flat_out <= {DC*QW{1'b0}};
            valid_out    <= 1'b0;
        end else begin
            valid_out <= valid_in;
            for (p = 0; p < DC; p = p + 1)
                msg_flat_out[p*QW +: QW] <= msg_out_comb[p];
        end
    end

endmodule

Hardware_architecture/LDPC_codes/tb_cnu_iams.v
// =============================================================================
// tb_cnu_iams.v  —  Testbench for cnu_iams.v
// =============================================================================
// Verifies the IAMS check-node update (eq. 10, Cui et al. TCAS-I 2020).
//
// Test plan:
//   1. RESET check
//   2. All-zero inputs   → all outputs zero
//   3. Directed Test A   : betas = {+3, −5, +2, −6, +4, −2, +1, −4, +3, +2}
//      Expected sign pattern and magnitudes computed by hand (see comments).
//   4. Directed Test B   : Δ=0 case  (min1 == min2)
//   5. Directed Test C   : Δ≠0 case  (standard IAMS path)
//   6. 1000 random trials: compare DUT output against golden C-model in task
//   7. Saturation check  : large magnitude inputs should clamp correctly
//
// Golden model implemented as a Verilog task (behavioral reference).
// =============================================================================

`timescale 1ns / 1ps

module tb_cnu_iams;

    // ---- Parameters matching DUT -------------------------------------------
    localparam DC   = 10;
    localparam QW   = 7;
    localparam IDW  = 4;
    localparam MSG_MAX =  (1 <<< (QW-1)) - 1;  // +63 for QW=7
    localparam MSG_MIN = -(1 <<< (QW-1));       // -64 for QW=7

    // ---- Clock / reset -------------------------------------------------------
    reg clk = 0;
    always #5 clk = ~clk;   // 100 MHz

    reg rst_n;
    initial begin
        rst_n = 0;
        #25 rst_n = 1;
    end

    // ---- DUT ports ----------------------------------------------------------
    reg              valid_in;
    reg  [DC*QW-1:0] msg_flat_in;
    wire [DC*QW-1:0] msg_flat_out;
    wire             valid_out;

    cnu_iams #(
        .DC (DC),
        .QW (QW),
        .IDW(IDW)
    ) dut (
        .clk         (clk),
        .rst_n       (rst_n),
        .valid_in    (valid_in),
        .msg_flat_in (msg_flat_in),
        .msg_flat_out(msg_flat_out),
        .valid_out   (valid_out)
    );

    // ---- Helper: pack DC signed messages into flat bus ----------------------
    task pack_msgs;
        input signed [QW-1:0] m0, m1, m2, m3, m4, m5, m6, m7, m8, m9;
        begin
            msg_flat_in[0*QW +: QW] = m0;
            msg_flat_in[1*QW +: QW] = m1;
            msg_flat_in[2*QW +: QW] = m2;
            msg_flat_in[3*QW +: QW] = m3;
            msg_flat_in[4*QW +: QW] = m4;
            msg_flat_in[5*QW +: QW] = m5;
            msg_flat_in[6*QW +: QW] = m6;
            msg_flat_in[7*QW +: QW] = m7;
            msg_flat_in[8*QW +: QW] = m8;
            msg_flat_in[9*QW +: QW] = m9;
        end
    endtask

    // ---- Golden model (behavioral IAMS CNU) ---------------------------------
    // Returns expected output messages as a flat bus.
    // Implements eq.(10) of the paper exactly.
    task golden_iams;
        input  [DC*QW-1:0] inp;
        output [DC*QW-1:0] outp;
        reg signed [QW-1:0] msg_i [0:DC-1];
        reg [QW-2:0] mag_i [0:DC-1];
        reg          sgn_i [0:DC-1];
        reg [QW-2:0] min1, min2;
        integer      idx1, idx2;
        reg          sign_total;
        reg [QW-2:0] delta;
        reg [QW-2:0] alpha_mag, temp;
        reg          out_sign;
        reg signed [QW-1:0] out_msg;
        integer ii, jj;
        begin
            // Unpack
            for (ii = 0; ii < DC; ii = ii + 1) begin
                msg_i[ii] = inp[ii*QW +: QW];
                sgn_i[ii] = msg_i[ii][QW-1];
                mag_i[ii] = sgn_i[ii] ? (~msg_i[ii][QW-2:0] + 1) : msg_i[ii][QW-2:0];
            end

            // Total sign parity
            sign_total = 0;
            for (ii = 0; ii < DC; ii = ii + 1)
                sign_total = sign_total ^ sgn_i[ii];

            // Find min1, min2
            min1 = {(QW-1){1'b1}};
            min2 = {(QW-1){1'b1}};
            idx1 = 0;
            idx2 = 0;
            for (ii = 0; ii < DC; ii = ii + 1) begin
                if (mag_i[ii] <= min1) begin
                    min2 = min1; idx2 = idx1;
                    min1 = mag_i[ii]; idx1 = ii;
                end else if (mag_i[ii] < min2) begin
                    min2 = mag_i[ii]; idx2 = ii;
                end
            end

            delta = (min2 >= min1) ? (min2 - min1) : 0;

            // Compute outputs
            for (jj = 0; jj < DC; jj = jj + 1) begin
                out_sign = sign_total ^ sgn_i[jj];

                if (jj == idx1)
                    alpha_mag = min2;
                else if (jj == idx2)
                    alpha_mag = min1;
                else begin
                    if (delta == 0)
                        alpha_mag = (min1 > 0) ? (min1 - 1) : 0;
                    else
                        alpha_mag = min1;
                end

                if (alpha_mag == 0)
                    out_msg = 0;
                else if (out_sign) begin
                    temp = ~alpha_mag + 1;
                    out_msg = {1'b1, temp};
                end else
                    out_msg = {1'b0, alpha_mag};

                outp[jj*QW +: QW] = out_msg;
            end
        end
    endtask

    // ---- Check and report ---------------------------------------------------
    integer pass_cnt = 0;
    integer fail_cnt = 0;

    task check_output;
        input [DC*QW-1:0] got;
        input [DC*QW-1:0] expected;
        input [63:0]       test_id;
        integer ii;
        reg ok;
        begin
            ok = (got === expected);
            if (ok) begin
                pass_cnt = pass_cnt + 1;
                $display("[PASS] Test %0d", test_id);
            end else begin
                fail_cnt = fail_cnt + 1;
                $display("[FAIL] Test %0d", test_id);
                for (ii = 0; ii < DC; ii = ii + 1) begin
                    if (got[ii*QW +: QW] !== expected[ii*QW +: QW])
                        $display("       edge[%0d]: got %0d  expected %0d",
                            ii,
                            $signed(got[ii*QW +: QW]),
                            $signed(expected[ii*QW +: QW]));
                end
            end
        end
    endtask

    // ---- Stimulus / checker -------------------------------------------------
    reg  [DC*QW-1:0] expected_out;
    integer          seed = 42;
    integer          trial;
    reg signed [QW-1:0] rand_msg;
    integer          ri;
    reg [DC*QW-1:0] inp3;
    reg [DC*QW-1:0] inp4;
    reg [DC*QW-1:0] inp5;
    integer kk;
    reg [DC*QW-1:0] inp6;
    integer kk1;
    reg [DC*QW-1:0] inp7;
            
    initial begin
        // ---- Setup ----------------------------------------------------------
        valid_in     = 0;
        msg_flat_in  = 0;
        @(posedge rst_n);
        @(posedge clk); #1;

        $display("=================================================================");
        $display("  IAMS CNU Testbench  (DC=%0d, QW=%0d)", DC, QW);
        $display("=================================================================");

        // ====================================================================
        // TEST 1: Reset state — valid_out should be low, output all zeros
        // ====================================================================
        @(posedge clk); #1;
        if (valid_out !== 1'b0)
            $display("[FAIL] T1: valid_out should be 0 after reset, got %0b", valid_out);
        else
            $display("[PASS] T1: reset state correct");

        // ====================================================================
        // TEST 2: All-zero inputs
        // ====================================================================
        pack_msgs(0, 0, 0, 0, 0, 0, 0, 0, 0, 0);
        valid_in = 1;
        @(posedge clk); #1;  // CNU registered output after 1 clk
        valid_in = 0;
        @(posedge clk); #1;  // Wait for pipeline
        golden_iams({DC*QW{1'b0}}, expected_out);
        check_output(msg_flat_out, expected_out, 2);

        // ====================================================================
        // TEST 3: Directed — mixed signs, standard IAMS case
        //   msgs = {+3, -5, +2, -6, +4, -2, +1, -4, +3, +2}
        //   Magnitudes: 3,5,2,6,4,2,1,4,3,2
        //   min1=1 (idx1=6), min2=2 (idx2=2 first occurrence)
        //   Δ = min2−min1 = 1 ≠ 0
        //   sign_total = XOR of {0,1,0,1,0,1,0,1,0,0} = 0
        // ====================================================================
        pack_msgs(7'd3, -7'd5, 7'd2, -7'd6, 7'd4, -7'd2, 7'd1, -7'd4, 7'd3, 7'd2);
        valid_in = 1;
        @(posedge clk); #1;
        valid_in = 0;
        @(posedge clk); #1;
        begin
            inp3[0*QW +: QW] = 7'd3;
            inp3[1*QW +: QW] = -7'd5;
            inp3[2*QW +: QW] = 7'd2;
            inp3[3*QW +: QW] = -7'd6;
            inp3[4*QW +: QW] = 7'd4;
            inp3[5*QW +: QW] = -7'd2;
            inp3[6*QW +: QW] = 7'd1;
            inp3[7*QW +: QW] = -7'd4;
            inp3[8*QW +: QW] = 7'd3;
            inp3[9*QW +: QW] = 7'd2;
            golden_iams(inp3, expected_out);
            check_output(msg_flat_out, expected_out, 3);
        end

        // ====================================================================
        // TEST 4: Δ = 0 case — two edges tied at minimum
        //   msgs = {+2, −2, +5, −8, +3, +4, +6, −2, +7, +3}
        //   Magnitudes: 2,2,5,8,3,4,6,2,7,3
        //   min1=2 (idx1=0), min2=2 (idx2=1), Δ=0
        //   Edges in Ī(m) should get max(2−1, 0) = 1
        // ====================================================================
        pack_msgs(7'd2, -7'd2, 7'd5, -7'd8, 7'd3, 7'd4, 7'd6, -7'd2, 7'd7, 7'd3);
        valid_in = 1;
        @(posedge clk); #1;
        valid_in = 0;
        @(posedge clk); #1;
        begin
            inp4[0*QW +:QW]=7'd2; inp4[1*QW +:QW]=-7'd2; inp4[2*QW +:QW]=7'd5;
            inp4[3*QW +:QW]=-7'd8; inp4[4*QW +:QW]=7'd3; inp4[5*QW +:QW]=7'd4;
            inp4[6*QW +:QW]=7'd6; inp4[7*QW +:QW]=-7'd2; inp4[8*QW +:QW]=7'd7;
            inp4[9*QW +:QW]=7'd3;
            golden_iams(inp4, expected_out);
            check_output(msg_flat_out, expected_out, 4);
        end

        // ====================================================================
        // TEST 5: All same magnitude (Δ=0, min1=min2=3)
        // ====================================================================
        pack_msgs(7'd3, 7'd3, 7'd3, 7'd3, 7'd3, 7'd3, 7'd3, 7'd3, 7'd3, 7'd3);
        valid_in = 1;
        @(posedge clk); #1;
        valid_in = 0;
        @(posedge clk); #1;
        begin
            for (kk=0; kk<DC; kk=kk+1) inp5[kk*QW +:QW]=7'd3;
            golden_iams(inp5, expected_out);
            check_output(msg_flat_out, expected_out, 5);
        end

        // ====================================================================
        // TEST 6: Saturation — inputs at max magnitude ±63 (QW=7)
        // ====================================================================
        pack_msgs(7'd63, -7'd63, 7'd63, -7'd63, 7'd63, -7'd63, 7'd63, -7'd63,
                  7'd63, -7'd63);
        valid_in = 1;
        @(posedge clk); #1;
        valid_in = 0;
        @(posedge clk); #1;
        begin
            for (kk1=0; kk1<DC; kk1=kk1+2) begin
                inp6[kk1*QW +:QW]    = 7'd63;
                inp6[(kk1+1)*QW +:QW]= -7'd63;
            end
            golden_iams(inp6, expected_out);
            check_output(msg_flat_out, expected_out, 6);
        end

        // ====================================================================
        // TEST 7: single dominant minimum (all others much larger)
        //   msgs = {+1, +10, +12, +9, +8, +11, +15, +7, +10, +11}
        //   min1=1(idx1=0), min2=7(idx2=7), Δ=6≠0
        // ====================================================================
        pack_msgs(7'd1, 7'd10, 7'd12, 7'd9, 7'd8, 7'd11, 7'd15, 7'd7, 7'd10, 7'd11);
        valid_in = 1;
        @(posedge clk); #1;
        valid_in = 0;
        @(posedge clk); #1;
        begin
            inp7[0*QW +:QW]=7'd1;  inp7[1*QW +:QW]=7'd10; inp7[2*QW +:QW]=7'd12;
            inp7[3*QW +:QW]=7'd9;  inp7[4*QW +:QW]=7'd8;  inp7[5*QW +:QW]=7'd11;
            inp7[6*QW +:QW]=7'd15; inp7[7*QW +:QW]=7'd7;  inp7[8*QW +:QW]=7'd10;
            inp7[9*QW +:QW]=7'd11;
            golden_iams(inp7, expected_out);
            check_output(msg_flat_out, expected_out, 7);
        end

        // ====================================================================
        // TEST 8 – 1007: 1000 random trials
        // ====================================================================
        $display("--- Running 1000 random trials ---");
        for (trial = 8; trial < 1008; trial = trial + 1) begin
            // Generate DC random signed messages in [−63, +63]
            for (ri = 0; ri < DC; ri = ri + 1) begin
                rand_msg = ($random(seed) % 64);  // range -63..63
                msg_flat_in[ri*QW +: QW] = rand_msg;
            end
            valid_in = 1;
            @(posedge clk); #1;
            valid_in = 0;
            @(posedge clk); #1;
            golden_iams(msg_flat_in, expected_out);
            check_output(msg_flat_out, expected_out, trial);
        end

        // ====================================================================
        // TEST 1008: valid_out tracks valid_in with 1-cycle delay
        // ====================================================================
        valid_in = 0;
        @(posedge clk); #1;
        if (valid_out !== 0)
            $display("[FAIL] T1008: valid_out should be 0 when valid_in=0");
        else
            $display("[PASS] T1008: valid_out gating correct");

        // ====================================================================
        // Summary
        // ====================================================================
        $display("");
        $display("=================================================================");
        $display("  Results: %0d PASS,  %0d FAIL  (total %0d)", pass_cnt, fail_cnt,
                  pass_cnt + fail_cnt);
        if (fail_cnt == 0)
            $display("  *** ALL TESTS PASSED ***");
        else
            $display("  *** FAILURES DETECTED — see above ***");
        $display("=================================================================");
        $finish;
    end

    // ---- Timeout watchdog ---------------------------------------------------
    initial begin
        #500_000;
        $display("TIMEOUT: simulation exceeded 500 us");
        $finish;
    end

    // ---- Optional VCD dump --------------------------------------------------
    initial begin
        $dumpfile("tb_cnu_iams.vcd");
        $dumpvars(0, tb_cnu_iams);
    end

endmodule

Hardware_architecture/LDPC_codes/tb_cnu_iams.vcd
$date
	Mon Mar 09 05:29:48 2026
$end
$version
	Icarus Verilog
$end
$timescale
	1ps
$end
$scope module tb_cnu_iams $end
$var wire 1 ! valid_out $end
$var wire 70 " msg_flat_out [69:0] $end
$var parameter 32 # DC $end
$var parameter 32 $ IDW $end
$var parameter 39 % MSG_MAX $end
$var parameter 38 & MSG_MIN $end
$var parameter 32 ' QW $end
$var reg 1 ( clk $end
$var reg 70 ) expected_out [69:0] $end
$var reg 70 * inp3 [69:0] $end
$var reg 70 + inp4 [69:0] $end
$var reg 70 , inp5 [69:0] $end
$var reg 70 - inp6 [69:0] $end
$var reg 70 . inp7 [69:0] $end
$var reg 70 / msg_flat_in [69:0] $end
$var reg 7 0 rand_msg [6:0] $end
$var reg 1 1 rst_n $end
$var reg 1 2 valid_in $end
$var integer 32 3 fail_cnt [31:0] $end
$var integer 32 4 kk [31:0] $end
$var integer 32 5 kk1 [31:0] $end
$var integer 32 6 pass_cnt [31:0] $end
$var integer 32 7 ri [31:0] $end
$var integer 32 8 seed [31:0] $end
$var integer 32 9 trial [31:0] $end
$scope module dut $end
$var wire 1 ( clk $end
$var wire 70 : msg_flat_in [69:0] $end
$var wire 1 1 rst_n $end
$var wire 1 2 valid_in $end
$var wire 6 ; delta [5:0] $end
$var parameter 32 < DC $end
$var parameter 32 = IDW $end
$var parameter 32 > QW $end
$var reg 6 ? alpha_mag [5:0] $end
$var reg 4 @ idx1 [3:0] $end
$var reg 4 A idx2 [3:0] $end
$var reg 6 B min1 [5:0] $end
$var reg 6 C min2 [5:0] $end
$var reg 70 D msg_flat_out [69:0] $end
$var reg 1 E out_sign $end
$var reg 1 F sign_total $end
$var reg 1 ! valid_out $end
$var integer 32 G i [31:0] $end
$var integer 32 H k [31:0] $end
$var integer 32 I n [31:0] $end
$var integer 32 J p [31:0] $end
$scope begin mag_sign[0] $end
$var parameter 2 K gi $end
$upscope $end
$scope begin mag_sign[1] $end
$var parameter 2 L gi $end
$upscope $end
$scope begin mag_sign[2] $end
$var parameter 3 M gi $end
$upscope $end
$scope begin mag_sign[3] $end
$var parameter 3 N gi $end
$upscope $end
$scope begin mag_sign[4] $end
$var parameter 4 O gi $end
$upscope $end
$scope begin mag_sign[5] $end
$var parameter 4 P gi $end
$upscope $end
$scope begin mag_sign[6] $end
$var parameter 4 Q gi $end
$upscope $end
$scope begin mag_sign[7] $end
$var parameter 4 R gi $end
$upscope $end
$scope begin mag_sign[8] $end
$var parameter 5 S gi $end
$upscope $end
$scope begin mag_sign[9] $end
$var parameter 5 T gi $end
$upscope $end
$scope begin unpack[0] $end
$var parameter 2 U gi $end
$upscope $end
$scope begin unpack[1] $end
$var parameter 2 V gi $end
$upscope $end
$scope begin unpack[2] $end
$var parameter 3 W gi $end
$upscope $end
$scope begin unpack[3] $end
$var parameter 3 X gi $end
$upscope $end
$scope begin unpack[4] $end
$var parameter 4 Y gi $end
$upscope $end
$scope begin unpack[5] $end
$var parameter 4 Z gi $end
$upscope $end
$scope begin unpack[6] $end
$var parameter 4 [ gi $end
$upscope $end
$scope begin unpack[7] $end
$var parameter 4 \ gi $end
$upscope $end
$scope begin unpack[8] $end
$var parameter 5 ] gi $end
$upscope $end
$scope begin unpack[9] $end
$var parameter 5 ^ gi $end
$upscope $end
$upscope $end
$scope task check_output $end
$var reg 70 _ expected [69:0] $end
$var reg 70 ` got [69:0] $end
$var reg 1 a ok $end
$var reg 64 b test_id [63:0] $end
$var integer 32 c ii [31:0] $end
$upscope $end
$scope task golden_iams $end
$var reg 6 d alpha_mag [5:0] $end
$var reg 6 e delta [5:0] $end
$var reg 70 f inp [69:0] $end
$var reg 6 g min1 [5:0] $end
$var reg 6 h min2 [5:0] $end
$var reg 7 i out_msg [6:0] $end
$var reg 1 j out_sign $end
$var reg 70 k outp [69:0] $end
$var reg 1 l sign_total $end
$var reg 6 m temp [5:0] $end
$var integer 32 n idx1 [31:0] $end
$var integer 32 o idx2 [31:0] $end
$var integer 32 p ii [31:0] $end
$var integer 32 q jj [31:0] $end
$upscope $end
$scope task pack_msgs $end
$var reg 7 r m0 [6:0] $end
$var reg 7 s m1 [6:0] $end
$var reg 7 t m2 [6:0] $end
$var reg 7 u m3 [6:0] $end
$var reg 7 v m4 [6:0] $end
$var reg 7 w m5 [6:0] $end
$var reg 7 x m6 [6:0] $end
$var reg 7 y m7 [6:0] $end
$var reg 7 z m8 [6:0] $end
$var reg 7 { m9 [6:0] $end
$upscope $end
$upscope $end
$enddefinitions $end
$comment Show the parameter values. $end
$dumpall
b1001 ^
b1000 ]
b111 \
b110 [
b101 Z
b100 Y
b11 X
b10 W
b1 V
b0 U
b1001 T
b1000 S
b111 R
b110 Q
b101 P
b100 O
b11 N
b10 M
b1 L
b0 K
b111 >
b100 =
b1010 <
b111 '
b11111111111111111111111111111111000000 &
b111111 %
b100 $
b1010 #
$end
#0
$dumpvars
bx {
bx z
bx y
bx x
bx w
bx v
bx u
bx t
bx s
bx r
bx q
bx p
bx o
bx n
bx m
xl
bx k
xj
bx i
bx h
bx g
bx f
bx e
bx d
bx c
bx b
xa
bx `
bx _
bx J
b1010 I
b1010 H
b1010 G
0F
0E
b0 D
b0 C
b0 B
b1000 A
b1001 @
b0 ?
b0 ;
b0 :
bx 9
b101010 8
bx 7
b0 6
bx 5
bx 4
b0 3
02
01
bx 0
b0 /
bx .
bx -
bx ,
bx +
bx *
bx )
0(
b0 "
0!
$end
#5000
1(
#10000
0(
#15000
1(
#20000
0(
#25000
b1010 J
1(
11
#30000
0(
#35000
b1010 J
1(
#40000
0(
#45000
b1010 J
1(
#46000
12
b0 {
b0 z
b0 y
b0 x
b0 w
b0 v
b0 u
b0 t
b0 s
b0 r
#50000
0(
#55000
1!
b1010 J
1(
#56000
02
#60000
0(
#65000
0!
b1010 J
1(
#66000
b1 ?
b1 ;
b1010 G
b101 A
b110 @
b10 C
b1 B
0E
b1010 I
0F
b1010 H
12
b10000001111111000000001111111000001001111010000001011110110000011 /
b10000001111111000000001111111000001001111010000001011110110000011 :
b10 {
b11 z
b1111100 y
b1 x
b1111110 w
b100 v
b1111010 u
b10 t
b1111011 s
b11 r
b1 6
1a
b10 b
b0 _
b0 `
b0 )
b0 k
b0 i
b0 d
0j
b1010 q
b0 e
b1000 o
b1001 n
b0 h
b0 g
0l
b1010 p
b0 f
#70000
0(
#75000
b1000000111111110000010111111100000011111111000000111111110000001 "
b1000000111111110000010111111100000011111111000000111111110000001 D
1!
b1010 J
1(
#76000
02
#80000
0(
#85000
0!
b1010 J
1(
#86000
b0 ;
b1010 G
b1 A
b111 @
b10 C
b10 B
b1 ?
1E
b1010 I
1F
b1010 H
12
b11000011111111100000110000010000000111111000000010111111100000010 /
b11000011111111100000110000010000000111111000000010111111100000010 :
b11 {
b111 z
b1111110 y
b110 x
b100 w
b11 v
b1111000 u
b101 t
b1111110 s
b10 r
b10 6
b11 b
b1000000111111110000010111111100000011111111000000111111110000001 _
b1000000111111110000010111111100000011111111000000111111110000001 `
b1000000111111110000010111111100000011111111000000111111110000001 )
b111111 m
0j
b1000000111111110000010111111100000011111111000000111111110000001 k
b1 i
b1 d
b1010 q
b1 e
b101 o
b110 n
b10 h
b1 g
0l
b1010 p
b10000001111111000000001111111000001001111010000001011110110000011 f
b10000001111111000000001111111000001001111010000001011110110000011 *
#90000
0(
#95000
b1111111111111100000101111111111111111111110000001111111100000101111111 "
b1111111111111100000101111111111111111111110000001111111100000101111111 D
1!
b1010 J
1(
#96000
02
#100000
0(
#105000
0!
b1010 J
1(
#106000
b1010 G
b1000 A
b1001 @
b11 C
b11 B
b11 ?
0E
b1010 I
b1010 H
0F
12
b11000001100000110000011000001100000110000011000001100000110000011 /
b11000001100000110000011000001100000110000011000001100000110000011 :
b11 z
b11 y
b11 x
b11 w
b11 u
b11 t
b11 s
b11 r
b11 6
b100 b
b1111111111111100000101111111111111111111110000001111111100000101111111 _
b1111111111111100000101111111111111111111110000001111111100000101111111 `
b1111111111111100000101111111111111111111110000001111111100000101111111 )
b1 d
b1111111111111100000101111111111111111111110000001111111100000101111111 k
b1111111 i
1j
b1010 q
b0 e
b1 o
b111 n
b10 h
b10 g
1l
b1010 p
b11000011111111100000110000010000000111111000000010111111100000010 f
b11000011111111100000110000010000000111111000000010111111100000010 +
#110000
0(
#115000
b11000001100000100000010000001000000100000010000001000000100000010 "
b11000001100000100000010000001000000100000010000001000000100000010 D
1!
b1010 J
1(
#116000
02
#120000
0(
#125000
0!
b1010 J
1(
#126000
b1010 G
b1000 A
b1001 @
b111111 C
b111111 B
b111111 ?
0E
b1010 I
1F
b1010 H
12
b1000001011111110000010111111100000101111111000001011111110000010111111 /
b1000001011111110000010111111100000101111111000001011111110000010111111 :
b1000001 {
b111111 z
b1000001 y
b111111 x
b1000001 w
b111111 v
b1000001 u
b111111 t
b1000001 s
b111111 r
b100 6
b101 b
b11000001100000100000010000001000000100000010000001000000100000010 _
b11000001100000100000010000001000000100000010000001000000100000010 `
b11000001100000100000010000001000000100000010000001000000100000010 )
b11000001100000100000010000001000000100000010000001000000100000010 k
b11 i
b11 d
0j
b1010 q
b1000 o
b1001 n
b11 h
b11 g
0l
b1010 p
b11000001100000110000011000001100000110000011000001100000110000011 f
b11000001100000110000011000001100000110000011000001100000110000011 ,
b1010 4
#130000
0(
#135000
b111111100000101111101000010011111010000100111110100001001111101000010 "
b111111100000101111101000010011111010000100111110100001001111101000010 D
1!
b1010 J
1(
#136000
02
#140000
0(
#145000
0!
b1010 J
1(
#146000
b110 ;
b111 C
b1 B
b1010 G
b111 A
b0 @
b1 ?
b1010 I
b1010 H
0F
12
b1011000101000001110001111000101100010000001001000110000010100000001 /
b1011000101000001110001111000101100010000001001000110000010100000001 :
b1011 {
b1010 z
b111 y
b1111 x
b1011 w
b1000 v
b1001 u
b1100 t
b1010 s
b1 r
b101 6
b110 b
b111111100000101111101000010011111010000100111110100001001111101000010 _
b111111100000101111101000010011111010000100111110100001001111101000010 `
b111111100000101111101000010011111010000100111110100001001111101000010 )
b111111100000101111101000010011111010000100111110100001001111101000010 k
b111111 i
b1 m
b111111 d
0j
b1010 q
b1000 o
b1001 n
b111111 h
b111111 g
1l
b1010 p
b1000001011111110000010111111100000101111111000001011111110000010111111 f
b1000001011111110000010111111100000101111111000001011111110000010111111 -
b1010 5
#150000
0(
#155000
b1000000100000010000001000000100000010000001000000100000010000111 "
b1000000100000010000001000000100000010000001000000100000010000111 D
1!
b1010 J
1(
#156000
02
#160000
0(
#165000
0!
b1010 J
1(
#166000
b10 ;
b1010 G
b111 A
b10 C
b0 B
b0 ?
1E
b1010 I
1F
b1010 H
12
b100001001111111100001010111010100101011001011000010000011010000000 /
b100001001111111100001010111010100101011001011000010000011010000000 :
b100 0
b10100010000000100101101111100000 8
b1010 7
b1000 9
b110 6
b111 b
b1000000100000010000001000000100000010000001000000100000010000111 _
b1000000100000010000001000000100000010000001000000100000010000111 `
b1000000100000010000001000000100000010000001000000100000010000111 )
b1000000100000010000001000000100000010000001000000100000010000111 k
b1 i
b1 d
b1010 q
b110 e
b111 h
b1 g
b111 o
b0 n
0l
b1010 p
b1011000101000001110001111000101100010000001001000110000010100000001 f
b1011000101000001110001111000101100010000001001000110000010100000001 .
#170000
0(
#175000
b1111110 "
b1111110 D
1!
b1010 J
1(
#176000
02
#180000
0(
#185000
0!
b1010 J
1(
