Hardware_architecture/LDPC_codes/vnu.v
// =============================================================================
// vnu.v  —  Variable Node Unit (VNU)
// =============================================================================
// Implements the layered VN update used in ALL decoder variants (MS, OMS, IAMS).
//
// In a layered decoder the APP LLR is updated layer-by-layer:
//
//   β_{n,m}  = APP_n  −  α_{m,n}^(prev)          (extrinsic VN→CN message)
//   APP_n   += α_{m,n}^(new)  −  α_{m,n}^(prev)   (APP update)
//
// Ports (all signals per variable node n, per active layer m):
//   app_in       : current APP LLR of VN n  (signed QW bits)
//   alpha_new    : new CN→VN message from layer m  (signed QW bits)
//   alpha_prev   : previous iteration CN→VN message from layer m  (signed QW bits)
//   beta_out     : extrinsic VN→CN message β_{n,m}  (signed QW bits)
//   app_out      : updated APP LLR after incorporating layer m  (signed QW bits)
//
// Saturation: outputs clipped to [−SAT, +SAT] where SAT = 2^(QW-1)−1.
// =============================================================================

`timescale 1ns / 1ps

module vnu #(
    parameter QW  = 7,    // Message bit-width (signed)
    parameter QTW = 8     // APP LLR width (wider to avoid saturation, paper: Q̃=31)
) (
    input  wire                  clk,
    input  wire                  rst_n,
    input  wire                  valid_in,
    // APP state
    input  wire signed [QTW-1:0] app_in,       // Current APP LLR (Q̃ bits)
    // CN→VN messages
    input  wire signed [QW-1:0]  alpha_new,    // New CN→VN from current iteration
    input  wire signed [QW-1:0]  alpha_prev,   // CN→VN stored from last iteration
    // Outputs
    output wire signed [QW-1:0]  beta_out,     // VN→CN extrinsic message
    output reg  signed [QTW-1:0] app_out,      // Updated APP LLR
    output reg                   valid_out
);

    // -------------------------------------------------------------------------
    // Saturation helper for APP output (Q̃-bit signed)
    // -------------------------------------------------------------------------
    localparam signed [QTW-1:0] SAT_MAX =  (1 <<< (QTW-1)) - 1;
    localparam signed [QTW-1:0] SAT_MIN = -(1 <<< (QTW-1));

    // -------------------------------------------------------------------------
    // Saturation helper for message output (QW-bit signed)
    // -------------------------------------------------------------------------
    localparam signed [QW-1:0] MSG_MAX =  (1 <<< (QW-1)) - 1;
    localparam signed [QW-1:0] MSG_MIN = -(1 <<< (QW-1));

    // -------------------------------------------------------------------------
    // Combinational: beta = app_in - alpha_prev  (VN→CN extrinsic)
    //                app  = app_in + alpha_new - alpha_prev
    // Implemented as: app = beta + alpha_new  (two adders, one shared subtraction)
    // -------------------------------------------------------------------------
    wire signed [QTW:0] beta_wide;       // one extra bit for overflow detect
    wire signed [QTW:0] app_wide;

    assign beta_wide = {{1{app_in[QTW-1]}}, app_in}
                     - {{(QTW-QW+1){alpha_prev[QW-1]}}, alpha_prev};

    assign app_wide  = beta_wide
                     + {{(QTW-QW+1){alpha_new[QW-1]}}, alpha_new};

    // Saturate beta to QW bits (message width)
    function signed [QW-1:0] sat_msg;
        input signed [QTW:0] x;
        begin
            if (x > $signed({{(QTW-QW+2){1'b0}}, MSG_MAX}))
                sat_msg = MSG_MAX;
            else if (x < $signed({{(QTW-QW+2){1'b1}}, MSG_MIN}))
                sat_msg = MSG_MIN;
            else
                sat_msg = x[QW-1:0];
        end
    endfunction

    assign beta_out = sat_msg(beta_wide);

    // -------------------------------------------------------------------------
    // Pipeline register
    // -------------------------------------------------------------------------
    always @(posedge clk or negedge rst_n) begin
        if (!rst_n) begin
            app_out   <= {QTW{1'b0}};
            valid_out <= 1'b0;
        end else begin
            valid_out <= valid_in;
            // Saturate APP to Q̃ range
            if (app_wide > $signed({1'b0, SAT_MAX}))
                app_out <= SAT_MAX;
            else if (app_wide < $signed({1'b1, SAT_MIN}))
                app_out <= SAT_MIN;
            else
                app_out <= app_wide[QTW-1:0];
        end
    end

endmodule

Hardware_architecture/LDPC_codes/tb_vnu.v
// =============================================================================
// tb_vnu.v  —  Testbench for vnu.v (Variable Node Unit)
// =============================================================================
// Tests the layered VN update:
//   beta_out = sat(app_in − alpha_prev)
//   app_out  = sat(app_in + alpha_new − alpha_prev)
//            = sat(beta_out + alpha_new)
// =============================================================================

`timescale 1ns / 1ps

module tb_vnu;

    localparam QW  = 7;
    localparam QTW = 8;

    localparam signed [QTW-1:0] SAT_APP_MAX =  (1 <<< (QTW-1)) - 1;  // +127
    localparam signed [QTW-1:0] SAT_APP_MIN = -(1 <<< (QTW-1));       // -128
    localparam signed [QW-1:0]  SAT_MSG_MAX =  (1 <<< (QW-1)) - 1;   // +63
    localparam signed [QW-1:0]  SAT_MSG_MIN = -(1 <<< (QW-1));        // -64

    // ---- Clock / reset -------------------------------------------------------
    reg clk = 0;
    always #5 clk = ~clk;

    reg rst_n;
    initial begin rst_n = 0; #25 rst_n = 1; end

    // ---- DUT ports ----------------------------------------------------------
    reg              valid_in;
    reg  signed [QTW-1:0] app_in;
    reg  signed [QW-1:0]  alpha_new;
    reg  signed [QW-1:0]  alpha_prev;
    wire signed [QW-1:0]  beta_out;
    wire signed [QTW-1:0] app_out;
    wire                  valid_out;

    vnu #(.QW(QW), .QTW(QTW)) dut (
        .clk       (clk),
        .rst_n     (rst_n),
        .valid_in  (valid_in),
        .app_in    (app_in),
        .alpha_new (alpha_new),
        .alpha_prev(alpha_prev),
        .beta_out  (beta_out),
        .app_out   (app_out),
        .valid_out (valid_out)
    );

    // ---- Golden model --------------------------------------------------------
    function signed [QW-1:0] sat_msg;
        input signed [QTW+1:0] x;
        begin
            if (x >  $signed(SAT_MSG_MAX)) sat_msg = SAT_MSG_MAX;
            else if (x < $signed(SAT_MSG_MIN)) sat_msg = SAT_MSG_MIN;
            else sat_msg = x[QW-1:0];
        end
    endfunction

    function signed [QTW-1:0] sat_app;
        input signed [QTW+1:0] x;
        begin
            if (x >  $signed(SAT_APP_MAX)) sat_app = SAT_APP_MAX;
            else if (x < $signed(SAT_APP_MIN)) sat_app = SAT_APP_MIN;
            else sat_app = x[QTW-1:0];
        end
    endfunction

    integer pass_cnt = 0, fail_cnt = 0;

    task apply_and_check;
        input signed [QTW-1:0] a_in;
        input signed [QW-1:0]  a_new, a_prev;
        input integer           test_id;
        reg signed [QTW+1:0]   beta_ref, app_ref;
        reg signed [QW-1:0]    exp_beta;
        reg signed [QTW-1:0]   exp_app;
        begin
            app_in     = a_in;
            alpha_new  = a_new;
            alpha_prev = a_prev;
            valid_in   = 1;
            @(posedge clk); #1;
            valid_in   = 0;
            // beta is combinational — read immediately
            beta_ref   = $signed(a_in) - $signed(a_prev);
            exp_beta   = sat_msg(beta_ref);
            // app is registered — wait one cycle
            @(posedge clk); #1;
            app_ref    = beta_ref + $signed(a_new);
            exp_app    = sat_app(app_ref);

            if (beta_out === exp_beta && app_out === exp_app) begin
                pass_cnt = pass_cnt + 1;
                $display("[PASS] T%0d  app_in=%0d  an=%0d  ap=%0d  beta=%0d  app=%0d",
                         test_id, a_in, a_new, a_prev, exp_beta, exp_app);
            end else begin
                fail_cnt = fail_cnt + 1;
                $display("[FAIL] T%0d  app_in=%0d  an=%0d  ap=%0d  beta: got=%0d exp=%0d  app: got=%0d exp=%0d",
                         test_id, a_in, a_new, a_prev,
                         beta_out, exp_beta, app_out, exp_app);
            end
        end
    endtask

    integer seed = 7;
    integer trial;
    reg signed [QTW-1:0] r_app;
    reg signed [QW-1:0]  r_an, r_ap;

    initial begin
        valid_in   = 0;
        app_in     = 0;
        alpha_new  = 0;
        alpha_prev = 0;
        @(posedge rst_n); @(posedge clk); #1;

        $display("=================================================================");
        $display("  VNU Testbench  (QW=%0d, QTW=%0d)", QW, QTW);
        $display("=================================================================");

        // --- Directed tests ---
        apply_and_check(  8'd10,  7'd3,  7'd2, 1);
        apply_and_check(  8'd0,   7'd0,  7'd0, 2);
        apply_and_check( -8'd20,  7'd5, -7'd3, 3);
        apply_and_check(  8'd100, 7'd10, 7'd8, 4);  // near saturation
        apply_and_check( -8'd100,-7'd10,-7'd8, 5);
        // Saturation: large positive APP + positive alpha_new
        apply_and_check( 8'd127, 7'd63, 7'd0, 6);  // app_out should saturate at +127
        apply_and_check(-8'd128,-7'd64, 7'd0, 7);  // app_out should saturate at -128

        // --- Random trials ---
        for (trial = 8; trial < 508; trial = trial + 1) begin
            r_app = $random(seed) % 128;
            r_an  = $random(seed) % 64;
            r_ap  = $random(seed) % 64;
            apply_and_check(r_app, r_an, r_ap, trial);
        end

        $display("");
        $display("=================================================================");
        $display("  Results: %0d PASS,  %0d FAIL", pass_cnt, fail_cnt);
        if (fail_cnt == 0)
            $display("  *** ALL TESTS PASSED ***");
        $display("=================================================================");
        $finish;
    end

    initial begin
        #200_000; $display("TIMEOUT"); $finish;
    end

    initial begin
        $dumpfile("tb_vnu.vcd");
        $dumpvars(0, tb_vnu);
    end

endmodule

Hardware_architecture/LDPC_codes/tb_vnu.vcd
$date
	Mon Mar 09 05:21:38 2026
$end
$version
	Icarus Verilog
$end
$timescale
	1ps
$end
$scope module tb_vnu $end
$var wire 1 ! valid_out $end
$var wire 7 " beta_out [6:0] $end
$var wire 8 # app_out [7:0] $end
$var parameter 32 $ QTW $end
$var parameter 32 % QW $end
$var parameter 8 & SAT_APP_MAX $end
$var parameter 8 ' SAT_APP_MIN $end
$var parameter 7 ( SAT_MSG_MAX $end
$var parameter 7 ) SAT_MSG_MIN $end
$var reg 7 * alpha_new [6:0] $end
$var reg 7 + alpha_prev [6:0] $end
$var reg 8 , app_in [7:0] $end
$var reg 1 - clk $end
$var reg 7 . r_an [6:0] $end
$var reg 7 / r_ap [6:0] $end
$var reg 8 0 r_app [7:0] $end
$var reg 1 1 rst_n $end
$var reg 1 2 valid_in $end
$var integer 32 3 fail_cnt [31:0] $end
$var integer 32 4 pass_cnt [31:0] $end
$var integer 32 5 seed [31:0] $end
$var integer 32 6 trial [31:0] $end
$scope function sat_app $end
$var reg 10 7 x [9:0] $end
$upscope $end
$scope function sat_msg $end
$var reg 10 8 x [9:0] $end
$upscope $end
$scope module dut $end
$var wire 7 9 alpha_new [6:0] $end
$var wire 7 : alpha_prev [6:0] $end
$var wire 8 ; app_in [7:0] $end
$var wire 1 - clk $end
$var wire 1 1 rst_n $end
$var wire 1 2 valid_in $end
$var wire 9 < beta_wide [8:0] $end
$var wire 7 = beta_out [6:0] $end
$var wire 9 > app_wide [8:0] $end
$var parameter 7 ? MSG_MAX $end
$var parameter 7 @ MSG_MIN $end
$var parameter 32 A QTW $end
$var parameter 32 B QW $end
$var parameter 8 C SAT_MAX $end
$var parameter 8 D SAT_MIN $end
$var reg 8 E app_out [7:0] $end
$var reg 1 ! valid_out $end
$scope function sat_msg $end
$var reg 9 F x [8:0] $end
$upscope $end
$upscope $end
$scope task apply_and_check $end
$var reg 8 G a_in [7:0] $end
$var reg 7 H a_new [6:0] $end
$var reg 7 I a_prev [6:0] $end
$var reg 10 J app_ref [9:0] $end
$var reg 10 K beta_ref [9:0] $end
$var reg 8 L exp_app [7:0] $end
$var reg 7 M exp_beta [6:0] $end
$var integer 32 N test_id [31:0] $end
$upscope $end
$upscope $end
$enddefinitions $end
$comment Show the parameter values. $end
$dumpall
b10000000 D
b1111111 C
b111 B
b1000 A
b1000000 @
b111111 ?
b1000000 )
b111111 (
b10000000 '
b1111111 &
b111 %
b1000 $
$end
#0
$dumpvars
bx N
bx M
bx L
bx K
bx J
bx I
bx H
bx G
b0 F
b0 E
b0 >
b0 =
b0 <
b0 ;
b0 :
b0 9
bx 8
bx 7
bx 6
b111 5
b0 4
b0 3
02
01
bx 0
bx /
bx .
0-
b0 ,
b0 +
b0 *
b0 #
b0 "
0!
$end
#5000
1-
#10000
0-
#15000
1-
#20000
0-
#25000
1-
11
#30000
0-
#35000
1-
#36000
b1000 "
b1000 =
b1000 F
12
b10 +
b10 :
b11 *
b11 9
b1011 >
b1000 <
b1010 ,
b1010 ;
b1 N
b10 I
b11 H
b1010 G
#40000
0-
#45000
b1011 #
b1011 E
1!
1-
#46000
b1000 M
b1000 8
b1000 K
02
#50000
0-
#55000
0!
1-
#56000
b0 "
b0 =
b0 F
12
b0 +
b0 :
b0 *
b0 9
b0 >
b0 <
b0 ,
b0 ;
b10 N
b0 I
b0 H
b0 G
b1 4
b1011 L
b1011 7
b1011 J
#60000
0-
#65000
b0 #
b0 E
1!
1-
#66000
b0 M
b0 8
b0 K
02
#70000
0-
#75000
0!
1-
#76000
b1101111 "
b1101111 =
b111101111 F
12
b1111101 +
b1111101 :
b101 *
b101 9
b111110100 >
b111101111 <
b11101100 ,
b11101100 ;
b11 N
b1111101 I
b101 H
b11101100 G
b10 4
b0 L
b0 7
b0 J
#80000
0-
#85000
b11110100 #
b11110100 E
1!
1-
#86000
b1101111 M
b1111101111 8
b1111101111 K
02
#90000
0-
#95000
0!
1-
#96000
b111111 "
b111111 =
b1011100 F
12
b1000 +
b1000 :
b1010 *
b1010 9
b1100110 >
b1011100 <
b1100100 ,
b1100100 ;
b100 N
b1000 I
b1010 H
b1100100 G
b11 4
b11110100 L
b1111110100 7
b1111110100 J
#100000
0-
#105000
b1100110 #
b1100110 E
1!
1-
#106000
b111111 M
b1011100 8
b1011100 K
02
#110000
0-
#115000
0!
1-
#116000
b1000000 "
b1000000 =
b110100100 F
12
b1111000 +
b1111000 :
b1110110 *
b1110110 9
b110011010 >
b110100100 <
b10011100 ,
b10011100 ;
b101 N
b1111000 I
b1110110 H
b10011100 G
b100 4
b1100110 L
b1100110 7
b1100110 J
#120000
0-
#125000
b10011010 #
b10011010 E
1!
1-
#126000
b1000000 M
b1110100100 8
b1110100100 K
02
#130000
0-
#135000
0!
1-
#136000
b111111 "
b111111 =
b1111111 F
12
b0 +
b0 :
b111111 *
b111111 9
b10111110 >
b1111111 <
b1111111 ,
b1111111 ;
b110 N
b0 I
b111111 H
b1111111 G
b101 4
b10011010 L
b1110011010 7
b1110011010 J
#140000
0-
#145000
b1111111 #
b1111111 E
1!
1-
#146000
b111111 M
b1111111 8
b1111111 K
02
#150000
0-
#155000
0!
1-
#156000
b1000000 "
b1000000 =
b110000000 F
12
b1000000 *
b1000000 9
b101000000 >
b110000000 <
b10000000 ,
b10000000 ;
b111 N
b1000000 H
b10000000 G
b110 4
b1111111 L
b10111110 7
b10111110 J
#160000
0-
#165000
b10000000 #
b10000000 E
1!
1-
#166000
b1000000 M
b1110000000 8
b1110000000 K
02
#170000
0-
#175000
0!
1-
#176000
b1100110 "
b1100110 =
b111100110 F
12
b11010 +
b11010 :
b1100 *
b1100 9
b111110010 >
b111100110 <
b0 ,
b0 ;
b1000 N
b11010 I
b1100 H
b0 G
b11010 /
b1100 .
b0 0
b10101101010101110110111011001010 5
b1000 6
b111 4
b10000000 L
b1101000000 7
b1101000000 J
#180000
0-
#185000
b11110010 #
b11110010 E
1!
1-
#186000
b1100110 M
b1111100110 8
b1111100110 K
02
#190000
0-
#195000
0!
1-
#196000
b111101 "
b111101 =
b111101 F
12
b11111 +
b11111 :
b1111011 *
b1111011 9
b111000 >
b111101 <
b1011100 ,
b1011100 ;
b1001 N
b11111 I
b1111011 H
b1011100 G
b11111 /
b1111011 .
b1011100 0
b11001111110001011111000000001001 5
b1001 6
b1000 4
b11110010 L
b1111110010 7
b1111110010 J
#200000
0-
#205000
b111000 #
b111000 E
1!
1-
#206000
b111101 M
b111101 8
b111101 K
02
#210000
0-
#215000
0!
1-
#216000
b1011010 "
b1011010 =
b111011010 F
12
b1100011 +
b1100011 :
b1000100 *
b1000100 9
b110011110 >
b111011010 <
b10111101 ,
b10111101 ;
b1010 N
b1100011 I
b1000100 H
b10111101 G
b1100011 /
b1000100 .
b10111101 0
b1010001110101111000011001110100 5
b1010 6
b1001 4
b111000 L
b111000 7
b111000 J
#220000
0-
#225000
b10011110 #
b10011110 E
1!
1-
#226000
b1011010 M
b1111011010 8
b1111011010 K
02
#230000
0-
#235000
0!
1-
#236000
b1000000 "
b1000000 =
b110101001 F
12
b1011010 +
b1011010 :
b1110110 *
b1110110 9
b110011111 >
b110101001 <
b10000011 ,
b10000011 ;
b1011 N
b1011010 I
b1110110 H
b10000011 G
b1011010 /
b1110110 .
b10000011 0
b1101001110110111111001111011 5
b1011 6
b1010 4
b10011110 L
b1110011110 7
b1110011110 J
#240000
0-
#245000
b10011111 #
b10011111 E
1!
1-
#246000
b1000000 M
b1110101001 8
b1110101001 K
02
#250000
0-
#255000
0!
1-
#256000
b1001100 "
b1001100 =
b111001100 F
12
b1101101 +
b1101101 :
b1110010 *
b1110010 9
b110111110 >
b111001100 <
b10111001 ,
b10111001 ;
b1100 N
b1101101 I
b1110010 H
b10111001 G
b1101101 /
b1110010 .
b10111001 0
b1110110110011101100000101001110 5
b1100 6
b1011 4
b10011111 L
b1110011111 7
b1110011111 J
#260000
0-
#265000
b10111110 #
b10111110 E
1!
1-
#266000
b1001100 M
b1111001100 8
b1111001100 K
02
#270000
0-
#275000
0!
1-
#276000
b1000000 "
b1000000 =
b110111001 F
12
b10000 +
b10000 :
b1011110 *
b1011110 9
b110010111 >
b110111001 <
b11001001 ,
b11001001 ;
b1101 N
b10000 I
b1011110 H
b11001001 G
b10000 /
b1011110 .
b11001001 0
b10101000001110111110001111011101 5
b1101 6
b1100 4
b10111110 L
b1110111110 7
b1110111110 J
#280000
0-
#285000
b10010111 #
b10010111 E
1!
1-
#286000
b1000000 M
b1110111001 8
b1110111001 K
02
#290000
0-
#295000
0!
1-
#296000
b111111 "
b111111 =
b1010001 F
12
b1111011 +
b1111011 :
b1011001 *
b1011001 9
b101010 >
b1010001 <
b1001100 ,
b1001100 ;
b1110 N
b1111011 I
b1011001 H
b1001100 G
b1111011 /
b1011001 .
b1001100 0
b111101101001001010000111011000 5
b1110 6
b1101 4
b10010111 L
b1110010111 7
b1110010111 J
#300000
0-
#305000
b101010 #
b101010 E
1!
1-
#306000
b111111 M
b1010001 8
b1010001 K
02
#310000
0-
#315000
0!
1-
#316000
b1000000 "
b1000000 =
b110100010 F
12
b10011 +
b10011 :
b1001000 *
b1001000 9
b101101010 >
b110100010 <
b10110101 ,
b10110101 ;
b1111 N
b10011 I
b1001000 H
b10110101 G
b10011 /
b1001000 .
b10110101 0
b11001001101001100011010010101111 5
b1111 6
b1110 4
b101010 L
b101010 7
b101010 J
#320000
0-
#325000
b10000000 #
b10000000 E
1!
1-
#326000
b1000000 M
b1110100010 8
b1110100010 K
02
#330000
0-
#335000
0!
1-
#336000
b1100001 "
b1100001 =
b111100001 F
12
b1011101 +
b1011101 :
b1010000 *
b1010000 9
b110110001 >
b111100001 <
b10111110 ,
b10111110 ;
b10000 N
b1011101 I
b1010000 H
b10111110 G
b1011101 /
b1010000 .
b10111110 0
b1110110010101011011010010010 5
b10000 6
b1111 4
b10000000 L
b1101101010 7
b1101101010 J
#340000
0-
#345000
b10110001 #
b10110001 E
1!
1-
#346000
b1100001 M
b1111100001 8
b1111100001 K
02
#350000
0-
#355000
0!
1-
#356000
b10100 "
b10100 =
b10100 F
12
b100000 +
b100000 :
b10001 *
b10001 9
b100101 >
b10100 <
b110100 ,
b110100 ;
b10001 N
b100000 I
b10001 H
b110100 G
b100000 /
b10001 .
b110100 0
b10110000000110011000000101110001 5
b10001 6
b10000 4
b10110001 L
b1110110001 7
b1110110001 J
#360000
0-
#365000
b100101 #
b100101 E
1!
1-
#366000
b10100 M
b10100 8
b10100 K
02
#370000
0-
#375000
0!
1-
#376000
b1001 "
b1001 =
b1001 F
12
b11001 +
b11001 :
b100001 *
b100001 9
b101010 >
b1001 <
b100010 ,
b100010 ;
b10010 N
b11001 I
b100001 H
b100010 G
b11001 /
b100001 .
b100010 0
b10101100101000110011100111111100 5
b10010 6
b10001 4
b100101 L
b100101 7
b100101 J
#380000
0-
#385000
b101010 #
b101010 E
1!
1-
#386000
b1001 M
b1001 8
b1001 K
02
#390000
0-
#395000
0!
1-
#396000
b101110 "
b101110 =
b101110 F
12
b1010111 +
b1010111 :
b1000010 *
b1000010 9
b111110000 >
b101110 <
b101 ,
b101 ;
b10011 N
b1010111 I
b1000010 H
b101 G
b1010111 /
b1000010 .
b101 0
b1011101101111111011010100011 5
b10011 6
b10010 4
b101010 L
b101010 7
b101010 J
#400000
0-
#405000
b11110000 #
b11110000 E
1!
1-
#406000
b101110 M
b101110 8
b101110 K
02
#410000
0-
#415000
0!
1-
#416000
b101000 "
b101000 =
b101000 F
12
b111000 +
b111000 :
b1010000 *
b1010000 9
b111111000 >
b101000 <
b1100000 ,
b1100000 ;
b10100 N
b111000 I
b1010000 H
b1100000 G
b111000 /
b1010000 .
b1100000 0
b11011100001110101011001010010110 5
b10100 6
b10011 4
b11110000 L
b1111110000 7
b1111110000 J
#420000
0-
#425000
b11111000 #
b11111000 E
1!
1-
#426000
b101000 M
b101000 8
b101000 K
02
#430000
0-
#435000
0!
1-
#436000
b1000000 "
b1000000 =
b101111011 F
12
b10110 +
b10110 :
b1111110 *
b1111110 9
b101111001 >
b101111011 <
b10010001 ,
b10010001 ;
b10101 N
b10110 I
b1111110 H
b10010001 G
b10110 /
b1111110 .
b10010001 0
b10001011011110001111110011000101 5
b10101 6
b10100 4
b11111000 L
b1111111000 7
b1111111000 J
#440000
0-
#445000
b10000000 #
b10000000 E
1!
1-
#446000
b1000000 M
b1101111011 8
b1101111011 K
02
#450000
0-
#455000
0!
1-
#456000
b111111 "
b111111 =
b1010101 F
12
b1001101 +
b1001101 :
b10101 *
b10101 9
b1101010 >
b1010101 <
b100010 ,
b100010 ;
b10110 N
b1001101 I
b10101 H
b100010 G
b1001101 /
b10101 .
b100010 0
b1000110111111001001001011100000 5
b10110 6
b10101 4
b10000000 L
b1101111001 7
b1101111001 J
#460000
0-
#465000
b1101010 #
b1101010 E
1!
1-
#466000
b111111 M
b1010101 8
b1010101 K
02
#470000
0-
#475000
0!
1-
#476000
b10101 "
b10101 =
b10101 F
12
b1101000 +
b1101000 :
b1110 *
b1110 9
b100011 >
b10101 <
b11111101 ,
b11111101 ;
b10111 N
b1101000 I
b1110 H
b11111101 G
b1101000 /
b1110 .
b11111101 0
b1010100010100100101100001010111 5
b10111 6
b10110 4
b1101010 L
b1101010 7
b1101010 J
#480000
0-
#485000
b100011 #
b100011 E
1!
1-
#486000
b10101 M
b10101 8
b10101 K
02
#490000
0-
#495000
0!
1-
#496000
b1010111 "
b1010111 =
b111010111 F
12
b1000010 +
b1000010 :
b1101111 *
b1101111 9
b111000110 >
b111010111 <
b10011001 ,
b10011001 ;
b11000 N
b1000010 I
b1101111 H
b10011001 G
b1000010 /
b1101111 .
b10011001 0
b1000001010010101101100101011010 5
b11000 6
b10111 4
b100011 L
b100011 7
b100011 J
#500000
0-
#505000
b11000110 #
b11000110 E
1!
1-
#506000
b1010111 M
b1111010111 8
b1111010111 K
02
#510000
0-
#515000
0!
1-
#516000
b111111 "
b111111 =
b1011010 F
12
b100 +
b100 :
b1000 *
b1000 9
b1100010 >
b1011010 <
b1011110 ,
b1011110 ;
b11001 N
b100 I
b1000 H
b1011110 G
b100 /
b1000 .
b1011110 0
b10100010010000000100100111011001 5
b11001 6
b11000 4
b11000110 L
b1111000110 7
b1111000110 J
#520000
0-
#525000
b1100010 #
b1100010 E
1!
1-
#526000
b111111 M
b1011010 8
b1011010 K
02
#530000
0-
#535000
0!
1-
#536000
b1101 "
b1101 =
b1101 F
12
b1101001 +
b1101001 :
b111001 *
b111001 9
b1000110 >
b1101 <
b11110110 ,
b11110110 ;
b11010 N
b1101001 I
b111001 H
b11110110 G
b1101001 /
b111001 .
b11110110 0
b1010100101000001011000010000100 5
b11010 6
b11001 4
b1100010 L
b1100010 7
b1100010 J
#540000
0-
#545000
b1000110 #
b1000110 E
1!
1-
#546000
b1101 M
b1101 8
b1101 K
02
#550000
0-
#555000
0!
1-
#556000
b111111 "
b111111 =
b1100011 F
12
b1011001 +
b1011001 :
b111000 *
b111000 9
b10011011 >
b1100011 <
b111100 ,
b111100 ;
b11011 N
b1011001 I
b111000 H
b111100 G
b1011001 /
b111000 .
b111100 0
b1001100111101001010110111001011 5
b11011 6
b11010 4
b1000110 L
b1000110 7
b1000110 J
#560000
0-
#565000
b1111111 #
b1111111 E
1!
1-
#566000
b111111 M
b1100011 8
b1100011 K
02
#570000
0-
#575000
0!
1-
#576000
b1000100 F
12
b110001 +
b110001 :
b1011010 *
b1011010 9
b11110 >
b1000100 <
b1110101 ,
b1110101 ;
b11100 N
b110001 I
b1011010 H
b1110101 G
b110001 /
b1011010 .
b1110101 0
b11111000101010000000111011011110 5
b11100 6
b11011 4
b1111111 L
b10011011 7
b10011011 J
#580000
0-
#585000
b11110 #
b11110 E
1!
1-
#586000
b1000100 8
b1000100 K
02
#590000
0-
#595000
0!
1-
#596000
b111111 "
b111111 =
b10100001 F
12
b1001011 +
b1001011 :
b11100 *
b11100 9
b10111101 >
b10100001 <
b1101100 ,
b1101100 ;
b11101 N
b1001011 I
b11100 H
b1101100 G
b1001011 /
b11100 .
b1101100 0
b1000101101101010001110010101101 5
b11101 6
b11100 4
b11110 L
b11110 7
b11110 J
#600000
0-
#605000
b1111111 #
b1111111 E
1!
1-
#606000
b10100001 8
b10100001 K
02
#610000
0-
#615000
0!
1-
#616000
b1001000 "
b1001000 =
b111001000 F
12
b1111010 +
b1111010 :
b1011001 *
b1011001 9
b110100001 >
b111001000 <
b11000010 ,
b11000010 ;
b11110 N
b1111010 I
b1011001 H
b11000010 G
b1111010 /
b1011001 .
b11000010 0
b1111101011010100101011011101000 5
b11110 6
b11101 4
b1111111 L
b10111101 7
b10111101 J
#620000
0-
#625000
b10100001 #
b10100001 E
1!
1-
#626000
b1001000 M
b1111001000 8
b1111001000 K
02
#630000
0-
#635000
0!
1-
#636000
b1000000 "
b1000000 =
b110110011 F
12
b100011 +
b100011 :
b1110011 *
b1110011 9
b110100110 >
b110110011 <
b11010110 ,
b11010110 ;
b11111 N
b100011 I
b1110011 H
b11010110 G
b100011 /
b1110011 .
b11010110 0
b11010001101100000000101011111111 5
b11111 6
b11110 4
b10100001 L
b1110100001 7
b1110100001 J
#640000
0-
#645000
b10100110 #
b10100110 E
1!
1-
#646000
b1000000 M
b1110110011 8
b1110110011 K
02
#650000
0-
#655000
0!
1-
#656000
b11000 "
b11000 =
b11000 F
12
b110011 +
b110011 :
b1001011 *
b1001011 9
b111100011 >
b11000 <
b1001011 ,
b1001011 ;
b100000 N
b110011 I
b1001011 H
b1001011 G
b110011 /
b1001011 .
b1001011 0
b11111001100000111111011100100010 5
b100000 6
b11111 4
b10100110 L
b1110100110 7
b1110100110 J
#660000
0-
#665000
b11100011 #
b11100011 E
1!
1-
#666000
b11000 M
b11000 8
b11000 K
02
#670000
0-
#675000
0!
1-
#676000
b1011 "
b1011 =
b1011 F
12
b1100111 +
b1100111 :
b1101011 *
b1101011 9
b111110110 >
b1011 <
b11110010 ,
b11110010 ;
b100001 N
b1100111 I
b1101011 H
b11110010 G
b1100111 /
b1101011 .
b11110010 0
b110011110100001110100101000001 5
b100001 6
b100000 4
b11100011 L
b1111100011 7
b1111100011 J
#680000
0-
#685000
b11110110 #
b11110110 E
1!
1-
#686000
b1011 M
b1011 8
b1011 K
02
#690000
0-
#695000
0!
1-
#696000
b1000000 "
b1000000 =
b101110010 F
12
b10100 +
b10100 :
b100 *
b100 9
b101110110 >
b101110010 <
b10000110 ,
b10000110 ;
b100010 N
b10100 I
b100 H
b10000110 G
b10100 /
b100 .
b10000110 0
b11001010000000110000101000001100 5
b100010 6
b100001 4
b11110110 L
b1111110110 7
b1111110110 J
#700000
0-
#705000
b10000000 #
b10000000 E
1!
1-
#706000
b1000000 M
b1101110010 8
b1101110010 K
02
#710000
0-
#715000
0!
1-
#716000
b111111 "
b111111 =
b1110110 F
12
b1110101 +
b1110101 :
b1010 *
b1010 9
b10000000 >
b1110110 <
b1101011 ,
b1101011 ;
b100011 N
b1110101 I
b1010 H
b1101011 G
b1110101 /
b1010 .
b1101011 0
b11010110110110100001111110011 5
b100011 6
b100010 4
b10000000 L
b1101110110 7
b1101110110 J
#720000
0-
#725000
b1111111 #
b1111111 E
1!
1-
#726000
b111111 M
b1110110 8
b1110110 K
02
#730000
0-
#735000
0!
1-
#736000
b10000011 F
12
b1001100 +
b1001100 :
b1011011 *
b1011011 9
b1011110 >
b10000011 <
b1001111 ,
b1001111 ;
b100100 N
b1001100 I
b1011011 H
b1001111 G
b1001100 /
b1011011 .
b1001111 0
b110010110001111011000100110 5
b100100 6
b100011 4
b1111111 L
b10000000 7
b10000000 J
#740000
0-
#745000
b1011110 #
b1011110 E
1!
1-
#746000
b10000011 8
b10000011 K
02
#750000
0-
#755000
0!
1-
#756000
b1000111 F
12
b1011000 +
b1011000 :
b10101 *
b10101 9
b1011100 >
b1000111 <
b11111 ,
b11111 ;
b100101 N
b1011000 I
b10101 H
b11111 G
b1011000 /
b10101 .
b11111 0
b1101100010101001110001110010101 5
b100101 6
b100100 4
b1011110 L
b1011110 7
b1011110 J
#760000
0-
#765000
b1011100 #
b1011100 E
1!
1-
#766000
b1000111 8
b1000111 K
02
#770000
0-
#775000
0!
1-
#776000
b1010011 F
12
b10011 +
b10011 :
b1000011 *
b1000011 9
b10110 >
b1010011 <
b1100110 ,
b1100110 ;
b100110 N
b10011 I
b1000011 H
b1100110 G
b10011 /
b1000011 .
b1100110 0
b11101001100001110000110111110000 5
b100110 6
b100101 4
b1011100 L
b1011100 7
b1011100 J
#780000
0-
#785000
b10110 #
b10110 E
1!
1-
#786000
b1010011 8
b1010011 K
02
#790000
0-
#795000
0!
1-
#796000
b111111 "
b111111 =
b1100000 F
12
b1110101 +
b1110101 :
b100011 *
b100011 9
b10000011 >
b1100000 <
b1010101 ,
b1010101 ;
b100111 N
b1110101 I
b100011 H
b1010101 G
b1110101 /
b100011 .
b1010101 0
b1011010100001101110110010100111 5
b100111 6
b100110 4
b10110 L
b10110 7
b10110 J
#800000
0-
#805000
b1111111 #
b1111111 E
1!
1-
#806000
b1100000 8
b1100000 K
02
#810000
0-
