Hardware_architecture/LDPC_codes_v2/ldpc5g_pkg.v
`define Z 16
`define MB 42
`define NB 52
`define N 1200
`define K 240
`define RATE_NUM  1
`define RATE_DEN   5

// ---- Quantization ----
`define Q          4         // Message bits (signed)
`define QTILDE     6         // APP bits (signed)
`define MSG_MAX    7         // 2^(Q-1)-1
`define APP_MAX    31        // 2^(QTILDE-1)-1

// ---- Decoder Structural Parameters ----
// BG2: rows 0..3 = core (4 rows), rows 4..41 = extension (38 rows)
// Orthogonal part: rows 20..41 (22 rows) -> merged to 11 pseudo-layers
// Total layers after merging: 4(core) + 16(non-orth ext) + 11(merged) = 31
// Paper states L reduces from 40 to 30 (we use 30 in impl)
`define NUM_CORE_ROWS    4
`define NUM_ORT_START    20   // first orthogonal row index (0-based)
`define NUM_ORT_ROWS     22   // rows 20..41
`define NUM_ORT_LAYERS   11   // merged pairs -> 11 layers
`define L_BEFORE         42   // MB
`define L_AFTER          31   // 4 + 16 + 11 = 31 (approx 30 in paper, slight diff due to BG2 exact structure)

// Max row degrees in BG2
`define DC_MAX       10   // maximum row degree overall BG2
`define DC_MAX_ORT    5   // maximum row degree in orthogonal part (rows 20-41 of BG2 <= dc_max/2)

// Column degree threshold for IAMS adaptation
`define D_THRESHOLD   6   // D parameter; VNs with dv >= D use OMS for core checks

// ---- Derived widths ----
// CTV compressed format per check: dc_max sign bits + 2*(q-1) min bits + 2*ceil(log2(dc_max)) idx bits
// For dc_max=10, q=4: 10 + 6 + 2*4 = 24 bits per Z block -> z*24
`define LOG2_DC_MAX   4                        // ceil(log2(10))=4
`define CTV_BITS_PER_CHECK (`DC_MAX + 2*(`Q-1) + 2*`LOG2_DC_MAX)  // = 10+6+8 = 24
`define CTV_WIDTH    (`Z * `CTV_BITS_PER_CHECK)  // = 52*24 = 1248 bits per layer

// For orthogonal part: dc_ort=5
`define LOG2_DC_ORT   3                        // ceil(log2(5))=3
`define CTV_BITS_ORT  (`DC_MAX_ORT + 2*(`Q-1) + 2*`LOG2_DC_ORT)  // = 5+6+6=17
`define CTV_ORT_WIDTH (2 * `Z * `CTV_BITS_ORT)  // 2 sets simultaneously

// IAMS: Column degree threshold D
// VNs with dv >= D in core checks use OMS instead of IAMS CN update

// ---- Memory depths ----
`define CTV_MEM1_DEPTH  `L_AFTER    // all layers
`define CTV_MEM2_DEPTH   15          // only core(4) + orthogonal(11) = 15 layers

// ---- Iteration limit (implementation) ----
`define ITMAX_IMPL   2

// ---- Misc ----
`define QMSG_W       `Q
`define QAPP_W       `QTILDE
`define HALF_Z       (`Z/2)

Hardware_architecture/LDPC_codes_v2/app_update.v
`include "ldpc5g_pkg.v"

module app_update #(
    parameter Q      = `Q,
    parameter QTILDE = `QTILDE
)(
    input  wire signed [QTILDE-1:0] app_in,
    input  wire signed [Q-1:0]      ctv_old,
    input  wire signed [Q-1:0]      ctv_new,
    output wire signed [QTILDE-1:0] app_out
);

// Compute beta_tilde = APP - alpha_old (keep QTILDE precision)
wire signed [QTILDE-1:0] ctv_old_ext, ctv_new_ext;
assign ctv_old_ext = {{(QTILDE-Q){ctv_old[Q-1]}}, ctv_old};
assign ctv_new_ext = {{(QTILDE-Q){ctv_new[Q-1]}}, ctv_new};

wire signed [QTILDE-1:0] beta_tilde;
assign beta_tilde = app_in - ctv_old_ext;

// Sum with extra bit for overflow detection
wire signed [QTILDE:0] sum_ext;
assign sum_ext = {beta_tilde[QTILDE-1], beta_tilde} +
                 {ctv_new_ext[QTILDE-1], ctv_new_ext};

// Saturate to QTILDE range [-32, +31]
assign app_out = (sum_ext > 7'sd31)  ?  6'sd31  :
                 (sum_ext < -7'sd32) ? -6'sd32  :
                  sum_ext[QTILDE-1:0];

endmodule

Hardware_architecture/LDPC_codes_v2/vnu.v
`include "ldpc5g_pkg.v"

module vnu #(
    parameter Q      = `Q,
    parameter QTILDE = `QTILDE
)(
    input  wire signed [QTILDE-1:0] app_in,
    input  wire signed [Q-1:0]      ctv_old,
    output wire signed [Q-1:0]      vtc_out
);

// Sign-extend ctv_old to QTILDE bits
wire signed [QTILDE-1:0] ctv_ext;
assign ctv_ext = {{(QTILDE-Q){ctv_old[Q-1]}}, ctv_old};

// Compute difference
wire signed [QTILDE-1:0] diff;
assign diff = app_in - ctv_ext;

// Saturate to Q-bit range [MSG_MIN, MSG_MAX] = [-8, +7]
// Use explicit literals for Verilog-2001 compatibility
assign vtc_out = (diff > 6'sd7)  ?  4'sd7  :
                 (diff < -6'sd8) ? -4'sd8  :
                  diff[Q-1:0];

endmodule

Hardware_architecture/LDPC_codes_v2/tb_vnu_app.v
// ============================================================
// tb_vnu_app.v  –  Testbench for VNU and APP Update
// Verifies:
//   VNU:  beta = clamp(APP - alpha_old) to Q-bit range
//   APP:  new_APP = clamp(alpha_new + (APP - alpha_old)) to QTILDE range
// ============================================================
`include "ldpc5g_pkg.v"
`timescale 1ns/1ps

module tb_vnu_app;

localparam Q      = `Q;       // 4
localparam QTILDE = `QTILDE;  // 6

// ---- VNU DUT ----
reg signed [QTILDE-1:0] app_in;
reg signed [Q-1:0]      ctv_old;
wire signed [Q-1:0]     vtc_out;

vnu #(.Q(Q), .QTILDE(QTILDE)) dut_vnu (
    .app_in  (app_in),
    .ctv_old (ctv_old),
    .vtc_out (vtc_out)
);

// ---- APP Update DUT ----
reg signed [Q-1:0]      ctv_new;
wire signed [QTILDE-1:0] app_out;

app_update #(.Q(Q), .QTILDE(QTILDE)) dut_app (
    .app_in  (app_in),
    .ctv_old (ctv_old),
    .ctv_new (ctv_new),
    .app_out (app_out)
);

// ---- Golden Reference ----
localparam signed [Q-1:0]      MSG_MAX =  (1 << (Q-1)) - 1;    // +7
localparam signed [Q-1:0]      MSG_MIN = -(1 << (Q-1));         // -8
localparam signed [QTILDE-1:0] APP_MAX =  (1 << (QTILDE-1))-1; // +31
localparam signed [QTILDE-1:0] APP_MIN = -(1 << (QTILDE-1));   // -32

function automatic signed [Q-1:0] golden_vnu;
    input signed [QTILDE-1:0] app;
    input signed [Q-1:0]      alpha_old;
    reg signed [QTILDE-1:0] diff;
    begin
        diff = app - {{(QTILDE-Q){alpha_old[Q-1]}}, alpha_old};
        if (diff > MSG_MAX) golden_vnu = MSG_MAX;
        else if (diff < MSG_MIN) golden_vnu = MSG_MIN;
        else golden_vnu = diff[Q-1:0];
    end
endfunction

function automatic signed [QTILDE-1:0] golden_app;
    input signed [QTILDE-1:0] app;
    input signed [Q-1:0]      alpha_old, alpha_new;
    reg signed [QTILDE-1:0] beta_tilde, sum;
    begin
        beta_tilde = app - {{(QTILDE-Q){alpha_old[Q-1]}}, alpha_old};
        sum = beta_tilde + {{(QTILDE-Q){alpha_new[Q-1]}}, alpha_new};
        if (sum > APP_MAX) golden_app = APP_MAX;
        else if (sum < APP_MIN) golden_app = APP_MIN;
        else golden_app = sum;
    end
endfunction

integer pass_cnt, fail_cnt;
reg failed;

task check_vnu;
    input signed [QTILDE-1:0] app;
    input signed [Q-1:0] alpha;
    input [31:0] tid;
    reg signed [Q-1:0] gold;
    begin
        app_in  = app;
        ctv_old = alpha;
        #5;
        gold = golden_vnu(app, alpha);
        if (vtc_out !== gold) begin
            $display("VNU FAIL t%0d: app=%0d alpha=%0d got=%0d exp=%0d",
                     tid, $signed(app), $signed(alpha), $signed(vtc_out), $signed(gold));
            fail_cnt = fail_cnt + 1;
        end else begin
            $display("VNU PASS t%0d", tid);
            pass_cnt = pass_cnt + 1;
        end
    end
endtask

task check_app;
    input signed [QTILDE-1:0] app;
    input signed [Q-1:0] a_old, a_new;
    input [31:0] tid;
    reg signed [QTILDE-1:0] gold;
    begin
        app_in  = app;
        ctv_old = a_old;
        ctv_new = a_new;
        #5;
        gold = golden_app(app, a_old, a_new);
        if (app_out !== gold) begin
            $display("APP FAIL t%0d: app=%0d aold=%0d anew=%0d got=%0d exp=%0d",
                     tid, $signed(app), $signed(a_old), $signed(a_new),
                     $signed(app_out), $signed(gold));
            fail_cnt = fail_cnt + 1;
        end else begin
            $display("APP PASS t%0d", tid);
            pass_cnt = pass_cnt + 1;
        end
    end
endtask

initial begin
    $dumpfile("tb_vnu_app.vcd");
    $dumpvars(0, tb_vnu_app);
    pass_cnt = 0; fail_cnt = 0;
    ctv_new = 0;

    // VNU tests
    check_vnu(6'sd10,  4'sd2,  1);   // 10-2=8 -> clamp to +7
    check_vnu(6'sd5,   4'sd2,  2);   // 5-2=3
    check_vnu(-6'sd10, 4'sd2,  3);   // -10-2=-12 -> clamp to -8
    check_vnu(6'sd0,   4'sd0,  4);   // 0
    check_vnu(6'sd31,  4'sd7,  5);   // 31-7=24 -> clamp +7
    check_vnu(-6'sd32,-4'sd8,  6);   // -32-(-8)=-24 -> clamp -8
    check_vnu(6'sd3,  -4'sd4,  7);   // 3-(-4)=7 -> +7
    check_vnu(6'sd3,  -4'sd5,  8);   // 3-(-5)=8 -> clamp +7

    // Random VNU
    begin : rvnu
        integer t;
        for (t = 0; t < 30; t = t+1) begin
            check_vnu($random % 64 - 32,
                      $random % 16 - 8,
                      10 + t);
        end
    end

    // APP update tests
    ctv_new = 0;
    check_app(6'sd10, 4'sd2, 4'sd3, 100);  // beta=8, new=3, sum=11
    check_app(6'sd5,  4'sd2, 4'sd2, 101);  // beta=3, new=2, sum=5
    check_app(6'sd31, 4'sd0, 4'sd7, 102);  // beta=31, new=7 -> clamp 31
    check_app(-6'sd32,4'sd0,-4'sd8,103);   // -32+(-8)=-40 -> clamp -32
    check_app(6'sd0,  4'sd3,-4'sd3, 104);  // beta=-3, new=-3 -> -6

    begin : rapp
        integer t;
        for (t = 0; t < 30; t = t+1) begin
            check_app($random % 64 - 32,
                      $random % 16 - 8,
                      $random % 16 - 8,
                      200 + t);
        end
    end

    $display("\n=== VNU/APP Test Summary ===");
    $display("PASS: %0d  FAIL: %0d", pass_cnt, fail_cnt);
    if (fail_cnt == 0) $display("ALL PASS");
    $finish;
end

initial begin
    #50000;
    $display("TIMEOUT");
    $finish;
end

endmodule

Hardware_architecture/LDPC_codes_v2/tb_vnu_app.vcd
$date
	Mon Mar 09 08:33:46 2026
$end
$version
	Icarus Verilog
$end
$timescale
	1ps
$end
$scope module tb_vnu_app $end
$var wire 4 ! vtc_out [3:0] $end
$var wire 6 " app_out [5:0] $end
$var parameter 6 # APP_MAX $end
$var parameter 6 $ APP_MIN $end
$var parameter 4 % MSG_MAX $end
$var parameter 4 & MSG_MIN $end
$var parameter 32 ' Q $end
$var parameter 32 ( QTILDE $end
$var reg 6 ) app_in [5:0] $end
$var reg 4 * ctv_new [3:0] $end
$var reg 4 + ctv_old [3:0] $end
$var integer 32 , fail_cnt [31:0] $end
$var integer 32 - pass_cnt [31:0] $end
$scope function golden_app $end
$upscope $end
$scope function golden_vnu $end
$upscope $end
$scope module dut_app $end
$var wire 6 . app_in [5:0] $end
$var wire 4 / ctv_new [3:0] $end
$var wire 4 0 ctv_old [3:0] $end
$var wire 7 1 sum_ext [6:0] $end
$var wire 6 2 ctv_old_ext [5:0] $end
$var wire 6 3 ctv_new_ext [5:0] $end
$var wire 6 4 beta_tilde [5:0] $end
$var wire 6 5 app_out [5:0] $end
$var parameter 32 6 Q $end
$var parameter 32 7 QTILDE $end
$upscope $end
$scope module dut_vnu $end
$var wire 6 8 app_in [5:0] $end
$var wire 4 9 ctv_old [3:0] $end
$var wire 4 : vtc_out [3:0] $end
$var wire 6 ; diff [5:0] $end
$var wire 6 < ctv_ext [5:0] $end
$var parameter 32 = Q $end
$var parameter 32 > QTILDE $end
$upscope $end
$scope begin rapp $end
$var integer 32 ? t [31:0] $end
$upscope $end
$scope begin rvnu $end
$var integer 32 @ t [31:0] $end
$upscope $end
$scope task check_app $end
$var reg 4 A a_new [3:0] $end
$var reg 4 B a_old [3:0] $end
$var reg 6 C app [5:0] $end
$var reg 6 D gold [5:0] $end
$var reg 32 E tid [31:0] $end
$upscope $end
$scope task check_vnu $end
$var reg 4 F alpha [3:0] $end
$var reg 6 G app [5:0] $end
$var reg 4 H gold [3:0] $end
$var reg 32 I tid [31:0] $end
$upscope $end
$upscope $end
$enddefinitions $end
$comment Show the parameter values. $end
$dumpall
b110 >
b100 =
b110 7
b100 6
b110 (
b100 '
b1000 &
b111 %
b100000 $
b11111 #
$end
#0
$dumpvars
b1 I
bx H
b1010 G
b10 F
bx E
bx D
bx C
bx B
bx A
bx @
bx ?
b10 <
b1000 ;
b111 :
b10 9
b1010 8
b1000 5
b1000 4
b0 3
b10 2
b1000 1
b10 0
b0 /
b1010 .
b0 -
b0 ,
b10 +
b0 *
b1010 )
b1000 "
b111 !
$end
#5000
b11 "
b11 5
b11 !
b11 :
b11 1
b11 4
b11 ;
b101 )
b101 .
b101 8
b10 I
b101 G
b1 -
b111 H
#10000
b1000 !
b1000 :
b110100 "
b110100 5
b1110100 1
b110100 4
b110100 ;
b110110 )
b110110 .
b110110 8
b11 I
b110110 G
b10 -
b11 H
#15000
b0 "
b0 5
b0 !
b0 :
b0 2
b0 <
b0 +
b0 0
b0 9
b0 1
b0 4
b0 ;
b0 )
b0 .
b0 8
b100 I
b0 F
b0 G
b11 -
b1000 H
#20000
b11000 "
b11000 5
b111 !
b111 :
b111 2
b111 <
b111 +
b111 0
b111 9
b11000 1
b11000 4
b11000 ;
b11111 )
b11111 .
b11111 8
b101 I
b111 F
b11111 G
b100 -
b0 H
#25000
b101000 "
b101000 5
b1000 !
b1000 :
b111000 2
b111000 <
b1000 +
b1000 0
b1000 9
b1101000 1
b101000 4
b101000 ;
b100000 )
b100000 .
b100000 8
b110 I
b1000 F
b100000 G
b101 -
b111 H
#30000
b111 "
b111 5
b111 !
b111 :
b111100 2
b111100 <
b1100 +
b1100 0
b1100 9
b111 1
b111 4
b111 ;
b11 )
b11 .
b11 8
b111 I
b1100 F
b11 G
b110 -
b1000 H
#35000
b1000 "
b1000 5
b1000 1
b1000 4
b111011 2
b1000 ;
b111011 <
b1011 +
b1011 0
b1011 9
b1000 I
b1011 F
b111 -
b111 H
#40000
b1011 "
b1011 5
b111001 2
b111001 <
b1001 +
b1001 0
b1001 9
b1011 1
b1011 4
b1011 ;
b100 )
b100 .
b100 8
b1010 I
b1001 F
b100 G
b0 @
b1000 -
#45000
b101110 "
b101110 5
b1000 !
b1000 :
b111011 2
b111011 <
b1011 +
b1011 0
b1011 9
b1101110 1
b101110 4
b101110 ;
b101001 )
b101001 .
b101001 8
b1011 I
b1011 F
b101001 G
b1 @
b1001 -
#50000
b101000 "
b101000 5
b101 2
b101 <
b101 +
b101 0
b101 9
b1101000 1
b101000 4
b101000 ;
b101101 )
b101101 .
b101101 8
b1100 I
b101 F
b101101 G
b10 @
b1010 -
b1000 H
#55000
b1011 "
b1011 5
b111 !
b111 :
b111010 2
b111010 <
b1010 +
b1010 0
b1010 9
b1011 1
b1011 4
b1011 ;
b101 )
b101 .
b101 8
b1101 I
b1010 F
b101 G
b11 @
b1011 -
#60000
b11100 "
b11100 5
b111 !
b111 :
b101 2
b101 <
b101 +
b101 0
b101 9
b11100 1
b11100 4
b11100 ;
b100001 )
b100001 .
b100001 8
b1110 I
b101 F
b100001 G
b100 @
b1100 -
b111 H
#65000
b10001 "
b10001 5
b10001 1
b10001 4
b10001 ;
b10110 )
b10110 .
b10110 8
b1111 I
b10110 G
b101 @
b1101 -
#70000
b1001 "
b1001 5
b100 2
b100 <
b100 +
b100 0
b100 9
b1001 1
b1001 4
b1001 ;
b1101 )
b1101 .
b1101 8
b10000 I
b100 F
b1101 G
b110 @
b1110 -
#75000
b11011 "
b11011 5
b111110 2
b111110 <
b1110 +
b1110 0
b1110 9
b11011 1
b11011 4
b11011 ;
b11001 )
b11001 .
b11001 8
b10001 I
b1110 F
b11001 G
b111 @
b1111 -
#80000
b100011 "
b100011 5
b1000 !
b1000 :
b10 2
b10 <
b10 +
b10 0
b10 9
b1100011 1
b100011 4
b100011 ;
b100101 )
b100101 .
b100101 8
b10010 I
b10 F
b100101 G
b1000 @
b10000 -
#85000
b110 !
b110 :
b110 "
b110 5
b111111 2
b111111 <
b1111 +
b1111 0
b1111 9
b110 1
b110 4
b110 ;
b101 )
b101 .
b101 8
b10011 I
b1111 F
b101 G
b1001 @
b10001 -
b1000 H
#90000
b1000 !
b1000 :
b101011 "
b101011 5
b111 2
b111 <
b111 +
b111 0
b111 9
b1101011 1
b101011 4
b101011 ;
b110010 )
b110010 .
b110010 8
b10100 I
b111 F
b110010 G
b1010 @
b10010 -
b110 H
#95000
b1100 "
b1100 5
b111 !
b111 :
b110 2
b110 <
b110 +
b110 0
b110 9
b1100 1
b1100 4
b1100 ;
b10010 )
b10010 .
b10010 8
b10101 I
b110 F
b10010 G
b1011 @
b10011 -
b1000 H
#100000
b1011 "
b1011 5
b111 !
b111 :
b111101 2
b111101 <
b1101 +
b1101 0
b1101 9
b1011 1
b1011 4
b1011 ;
b1000 )
b1000 .
b1000 8
b10110 I
b1101 F
b1000 G
b1100 @
b10100 -
b111 H
#105000
b110111 "
b110111 5
b1000 !
b1000 :
b101 2
b101 <
b101 +
b101 0
b101 9
b1110111 1
b110111 4
b110111 ;
b111100 )
b111100 .
b111100 8
b10111 I
b101 F
b111100 G
b1101 @
b10101 -
#110000
b10000 "
b10000 5
b111 !
b111 :
b111101 2
b111101 <
b1101 +
b1101 0
b1101 9
b10000 1
b10000 4
b10000 ;
b1101 )
b1101 .
b1101 8
b11000 I
b1101 F
b1101 G
b1110 @
b10110 -
b1000 H
#115000
b1 "
b1 5
b1 !
b1 :
b10 2
b10 <
b10 +
b10 0
b10 9
b1 1
b1 4
b1 ;
b11 )
b11 .
b11 8
b11001 I
b10 F
b11 G
b1111 @
b10111 -
b111 H
#120000
b101000 "
b101000 5
b1000 !
b1000 :
b111000 2
b111000 <
b1000 +
b1000 0
b1000 9
b1101000 1
b101000 4
b101000 ;
b100000 )
b100000 .
b100000 8
b11010 I
b1000 F
b100000 G
b10000 @
b11000 -
b1 H
#125000
b101 "
b101 5
b101 !
b101 :
b101 2
b101 <
b101 +
b101 0
b101 9
b101 1
b101 4
b101 ;
b1010 )
b1010 .
b1010 8
b11011 I
b101 F
b1010 G
b10001 @
b11001 -
b1000 H
#130000
b1011 !
b1011 :
b111011 "
b111011 5
b111011 2
b111011 <
b1011 +
b1011 0
b1011 9
b1111011 1
b111011 4
b111011 ;
b110110 )
b110110 .
b110110 8
b11100 I
b1011 F
b110110 G
b10010 @
b11010 -
b101 H
#135000
b110010 "
b110010 5
b1000 !
b1000 :
b1110010 1
b110010 4
b110010 ;
b101101 )
b101101 .
b101101 8
b11101 I
b101101 G
b10011 @
b11011 -
b1011 H
#140000
b1110 "
b1110 5
b111 !
b111 :
b111101 2
b111101 <
b1101 +
b1101 0
b1101 9
b1110 1
b1110 4
b1110 ;
b1011 )
b1011 .
b1011 8
b11110 I
b1101 F
b1011 G
b10100 @
b11100 -
b1000 H
#145000
b11100 "
b11100 5
b111 !
b111 :
b110 2
b110 <
b110 +
b110 0
b110 9
b11100 1
b11100 4
b11100 ;
b100010 )
b100010 .
b100010 8
b11111 I
b110 F
b100010 G
b10101 @
b11101 -
b111 H
#150000
b110110 "
b110110 5
b1000 !
b1000 :
b111 2
b111 <
b111 +
b111 0
b111 9
b1110110 1
b110110 4
b110110 ;
b111101 )
b111101 .
b111101 8
b100000 I
b111 F
b111101 G
b10110 @
b11110 -
#155000
b1 "
b1 5
b1 !
b1 :
b10 2
b10 <
b10 +
b10 0
b10 9
b1 1
b1 4
b1 ;
b11 )
b11 .
b11 8
b100001 I
b10 F
b11 G
b10111 @
b11111 -
b1000 H
#160000
b1000 !
b1000 :
b100110 "
b100110 5
b100 2
b100 <
b100 +
b100 0
b100 9
b1100110 1
b100110 4
b100110 ;
b101010 )
b101010 .
b101010 8
b100010 I
b100 F
b101010 G
b11000 @
b100000 -
b1 H
#165000
b10000 "
b10000 5
b111 !
b111 :
b10 2
b10 <
b10 +
b10 0
b10 9
b10000 1
b10000 4
b10000 ;
b10010 )
b10010 .
b10010 8
b100011 I
b10 F
b10010 G
b11001 @
b100001 -
b1000 H
#170000
b100001 "
b100001 5
b1000 !
b1000 :
b0 2
b0 <
b0 +
b0 0
b0 9
b1100001 1
b100001 4
b100001 ;
b100001 )
b100001 .
b100001 8
b100100 I
b0 F
b100001 G
b11010 @
b100010 -
b111 H
#175000
b10111 "
b10111 5
b111 !
b111 :
b1 2
b1 <
b1 +
b1 0
b1 9
b10111 1
b10111 4
b10111 ;
b11000 )
b11000 .
b11000 8
b100101 I
b1 F
b11000 G
b11011 @
b100011 -
b1000 H
#180000
b1101 "
b1101 5
b111110 2
b111110 <
b1110 +
b1110 0
b1110 9
b1101 1
b1101 4
b1101 ;
b1011 )
b1011 .
b1011 8
b100110 I
b1110 F
b1011 G
b11100 @
b100100 -
b111 H
#185000
b100000 "
b100000 5
b1000 !
b1000 :
b110 2
b110 <
b110 +
b110 0
b110 9
b1100000 1
b100000 4
b100000 ;
b100110 )
b100110 .
b100110 8
b100111 I
b110 F
b100110 G
b11101 @
b100101 -
#190000
b1011 "
b1011 5
b111 !
b111 :
b11 3
b11 *
b11 /
b10 2
b10 <
b10 +
b10 0
b10 9
b1011 1
b1000 4
b1000 ;
b1010 )
b1010 .
b1010 8
b1100100 E
b11 A
b10 B
b1010 C
b11110 @
b100110 -
b1000 H
#195000
b101 "
b101 5
b11 !
b11 :
b10 3
b10 *
b10 /
b101 1
b11 4
b11 ;
b101 )
b101 .
b101 8
b1100101 E
b10 A
b101 C
b100111 -
b1011 D
#200000
b11111 "
b11111 5
b111 !
b111 :
b111 3
b111 *
b111 /
b0 2
b0 <
b0 +
b0 0
b0 9
b100110 1
b11111 4
b11111 ;
b11111 )
b11111 .
b11111 8
b1100110 E
b111 A
b0 B
b11111 C
b101000 -
b101 D
#205000
b100000 "
b100000 5
b1000 !
b1000 :
b111000 3
b1000 *
b1000 /
b1011000 1
b100000 4
b100000 ;
b100000 )
b100000 .
b100000 8
b1100111 E
b1000 A
b100000 C
b1 ,
b100110 D
#210000
b1101 !
b1101 :
b111010 "
b111010 5
b111101 3
b1101 *
b1101 /
b11 2
b11 <
b11 +
b11 0
b11 9
b1111010 1
b111101 4
b111101 ;
b0 )
b0 .
b0 8
b1101000 E
b1101 A
b11 B
b0 C
b10 ,
b11000 D
#215000
b11101 "
b11101 5
b111 !
b111 :
b11 3
b11 *
b11 /
b10 2
b10 <
b10 +
b10 0
b10 9
b11101 1
b11010 4
b11010 ;
b11100 )
b11100 .
b11100 8
b11001000 E
b11 A
b10 B
b11100 C
b0 ?
b101001 -
b111010 D
#220000
b11011 "
b11011 5
b111 !
b111 :
b111 3
b111 *
b111 /
b111101 2
b111101 <
b1101 +
b1101 0
b1101 9
b11011 1
b10100 4
b10100 ;
b10001 )
b10001 .
b10001 8
b11001001 E
b111 A
b1101 B
b10001 C
b1 ?
b101010 -
b11101 D
#225000
b111 !
b111 :
b11111 "
b11111 5
b110 3
b110 *
b110 /
b10 2
b10 <
b10 +
b10 0
b10 9
b11111 1
b11001 4
b11001 ;
b11011 )
b11011 .
b11011 8
b11001010 E
b110 A
b10 B
b11011 C
b10 ?
b101011 -
b11011 D
#230000
b111101 "
b111101 5
b1100 !
b1100 :
b1 3
b1 *
b1 /
b111001 2
b111001 <
b1001 +
b1001 0
b1001 9
b1111101 1
b111100 4
b111100 ;
b110101 )
b110101 .
b110101 8
b11001011 E
b1 A
b1001 B
b110101 C
b11 ?
b101100 -
b11111 D
#235000
b101 "
b101 5
b1110 !
b1110 :
b111 3
b111 *
b111 /
b100 2
b100 <
b100 +
b100 0
b100 9
b101 1
b111110 4
b111110 ;
b10 )
b10 .
b10 8
b11001100 E
b111 A
b100 B
b10 C
b100 ?
b101101 -
b111101 D
#240000
b101110 "
b101110 5
b1000 !
b1000 :
b111111 3
b1111 *
b1111 /
b0 2
b0 <
b0 +
b0 0
b0 9
b1101110 1
b101111 4
b101111 ;
b101111 )
b101111 .
b101111 8
b11001101 E
b1111 A
b0 B
b101111 C
b101 ?
b101110 -
b101 D
#245000
b111110 "
b111110 5
b1011 !
b1011 :
b11 3
b11 *
b11 /
b100 2
b100 <
b100 +
b100 0
b100 9
b1111110 1
b111011 4
b111011 ;
b111111 )
b111111 .
b111111 8
b11001110 E
b11 A
b100 B
b111111 C
b110 ?
b101111 -
b101110 D
#250000
b100000 "
b100000 5
b1000 !
b1000 :
b111000 3
b1000 *
b1000 /
b1 2
b1 <
b1 +
b1 0
b1 9
b1100000 1
b101000 4
b101000 ;
b101001 )
b101001 .
b101001 8
b11001111 E
b1000 A
b1 B
b101001 C
b111 ?
b110000 -
b111110 D
#255000
b111100 "
b111100 5
b1110 !
b1110 :
b111110 3
b1110 *
b1110 /
b111001 2
b111001 <
b1001 +
b1001 0
b1001 9
b1111100 1
b111110 4
b111110 ;
b110111 )
b110111 .
b110111 8
b11010000 E
b1110 A
b1001 B
b110111 C
b1000 ?
b110001 -
b100000 D
#260000
b110010 "
b110010 5
b1000 !
b1000 :
b0 3
b0 *
b0 /
b111010 2
b111010 <
b1010 +
b1010 0
b1010 9
b1110010 1
b110010 4
b110010 ;
b101100 )
b101100 .
b101100 8
b11010001 E
b0 A
b1010 B
b101100 C
b1001 ?
b110010 -
b111100 D
#265000
b111 !
b111 :
b1100 "
b1100 5
b111010 3
b1010 *
b1010 /
b101 2
b101 <
b101 +
b101 0
b101 9
b1100 1
b10010 4
b10010 ;
b10111 )
b10111 .
b10111 8
b11010010 E
b1010 A
b101 B
b10111 C
b1010 ?
b110011 -
b110010 D
#270000
b11010 "
b11010 5
b1 3
b1 *
b1 /
b11010 1
b11001 4
b11001 ;
b11110 )
b11110 .
b11110 8
b11010011 E
b1 A
b11110 C
b1011 ?
b110100 -
b1100 D
#275000
b1 "
b1 5
b100 !
b100 :
b111101 3
b1101 *
b1101 /
b111011 2
b111011 <
b1011 +
b1011 0
b1011 9
b1 1
b100 4
b100 ;
b111111 )
b111111 .
b111111 8
b11010100 E
b1101 A
b1011 B
b111111 C
b1100 ?
b110101 -
b11010 D
#280000
b10110 "
b10110 5
b111 !
b111 :
b1 3
b1 *
b1 /
b11 2
b11 <
b11 +
b11 0
b11 9
b10110 1
b10101 4
b10101 ;
b11000 )
b11000 .
b11000 8
b11010101 E
b1 A
b11 B
b11000 C
b1101 ?
b110110 -
b1 D
#285000
b11101 "
b11101 5
b0 3
b0 *
b0 /
b10 2
b10 <
b10 +
b10 0
b10 9
b11101 1
b11101 4
b11101 ;
b11111 )
b11111 .
b11111 8
b11010110 E
b0 A
b10 B
b11111 C
b1110 ?
b110111 -
b10110 D
#290000
b100100 "
b100100 5
b1000 !
b1000 :
b100 3
b100 *
b100 /
b110 2
b110 <
b110 +
b110 0
b110 9
b1100100 1
b100000 4
b100000 ;
b100110 )
b100110 .
b100110 8
b11010111 E
b100 A
b110 B
b100110 C
b1111 ?
b111000 -
b11101 D
#295000
b10111 "
b10111 5
b111 !
b111 :
b111011 3
b1011 *
b1011 /
b111110 2
b111110 <
b1110 +
b1110 0
b1110 9
b10111 1
b11100 4
b11100 ;
b11010 )
b11010 .
b11010 8
b11011000 E
b1011 A
b1110 B
b11010 C
b10000 ?
b111001 -
b100100 D
#300000
b110111 "
b110111 5
b1100 !
b1100 :
b111 2
b111 <
b111 +
b111 0
b111 9
b1110111 1
b111100 4
b111100 ;
b11 )
b11 .
b11 8
b11011001 E
b111 B
b11 C
b10001 ?
b111010 -
b10111 D
#305000
b10 "
b10 5
b11 !
b11 :
b111111 3
b1111 *
b1111 /
b111100 2
b111100 <
b1100 +
b1100 0
b1100 9
b10 1
b11 4
b11 ;
b111111 )
b111111 .
b111111 8
b11011010 E
b1111 A
b1100 B
b111111 C
b10010 ?
b111011 -
b110111 D
#310000
b101111 "
b101111 5
b1000 !
b1000 :
b10 3
b10 *
b10 /
b111110 2
b111110 <
b1110 +
b1110 0
b1110 9
b1101111 1
b101101 4
b101101 ;
b101011 )
b101011 .
b101011 8
b11011011 E
b10 A
b1110 B
b101011 C
b10011 ?
b111100 -
b10 D
#315000
b110 "
b110 5
b100 !
b100 :
b101 2
b101 <
b101 +
b101 0
b101 9
b110 1
b100 4
b100 ;
b1001 )
b1001 .
b1001 8
b11011100 E
b101 B
b1001 C
b10100 ?
b111101 -
b101111 D
#320000
b111 !
b111 :
b1111 "
b1111 5
b111 3
b111 *
b111 /
b111101 2
b111101 <
b1101 +
b1101 0
b1101 9
b1111 1
b1000 4
b1000 ;
b101 )
b101 .
b101 8
b11011101 E
b111 A
b1101 B
b101 C
b10101 ?
b111110 -
b110 D
#325000
b10101 "
b10101 5
b111000 3
b1000 *
b1000 /
b111100 2
b111100 <
b1100 +
b1100 0
b1100 9
b10101 1
b11101 4
b11101 ;
b11001 )
b11001 .
b11001 8
b11011110 E
b1000 A
b1100 B
b11001 C
b10110 ?
b111111 -
b1111 D
#330000
b1101 "
b1101 5
b110 3
b110 *
b110 /
b11 2
b11 <
b11 +
b11 0
b11 9
b1101 1
b111 4
b111 ;
b1010 )
b1010 .
b1010 8
b11011111 E
b110 A
b11 B
b1010 C
b10111 ?
b1000000 -
b10101 D
#335000
b1010 !
b1010 :
b111111 "
b111111 5
b101 3
b101 *
b101 /
b10 2
b10 <
b10 +
b10 0
b10 9
b1111111 1
b111010 4
b111010 ;
b111100 )
b111100 .
b111100 8
b11100000 E
b101 A
b10 B
b111100 C
b11000 ?
b1000001 -
b1101 D
#340000
b101011 "
b101011 5
b1000 !
b1000 :
b110 3
b110 *
b110 /
b111110 2
b111110 <
b1110 +
b1110 0
b1110 9
b1101011 1
b100101 4
b100101 ;
b100011 )
b100011 .
b100011 8
b11100001 E
b110 A
b1110 B
b100011 C
b11001 ?
b1000010 -
b111111 D
